{
    "actions": [
        {
            "COMMAND": null,
            "RESPONSE": null
        },
        {
            "COMMAND": "[1763010506.547][INFO]: [5fbd50b274790022917e320665b02ce4] COMMAND InitSession {\n   \"capabilities\": {\n      \"firstMatch\": [ {\n         \"browserName\": \"chrome\",\n         \"goog:chromeOptions\": {\n            \"args\": [ \"--remote-allow-origins=*\" ],\n            \"binary\": \"C:\\\\Program Files\\\\Google\\\\Chrome\\\\Application\\\\chrome.exe\",\n            \"extensions\": [  ]\n         },\n         \"goog:loggingPrefs\": {\n            \"browser\": \"ALL\",\n            \"driver\": \"ALL\"\n         }\n      } ]\n   }\n}\n",
            "RESPONSE": "[1763010507.982][INFO]: [5fbd50b274790022917e320665b02ce4] RESPONSE InitSession {\n   \"capabilities\": {\n      \"acceptInsecureCerts\": false,\n      \"browserName\": \"chrome\",\n      \"browserVersion\": \"142.0.7444.135\",\n      \"chrome\": {\n         \"chromedriverVersion\": \"142.0.7444.162 (c076baf266c3ed5efb225de664cfa7b183668ad6-refs/branch-heads/7444@{#2498})\",\n         \"userDataDir\": \"C:\\\\Users\\\\Dell\\\\AppData\\\\Local\\\\Temp\\\\scoped_dir21580_487723863\"\n      },\n      \"fedcm:accounts\": true,\n      \"goog:chromeOptions\": {\n         \"debuggerAddress\": \"localhost:60497\"\n      },\n      \"goog:processID\": 24196,\n      \"networkConnectionEnabled\": false,\n      \"pageLoadStrategy\": \"normal\",\n      \"platformName\": \"windows\",\n      \"proxy\": {\n      },\n      \"setWindowRect\": true,\n      \"strictFileInteractability\": false,\n      \"timeouts\": {\n         \"implicit\": 0,\n         \"pageLoad\": 300000,\n         \"script\": 30000\n      },\n      \"unhandledPromptBehavior\": \"dismiss and notify\",\n      \"webauthn:extension:credBlob\": true,\n      \"webauthn:extension:largeBlob\": true,\n      \"webauthn:extension:minPinLength\": true,\n      \"webauthn:extension:prf\": true,\n      \"~~~\": \"...\"\n   },\n   \"sessionId\": \"5fbd50b274790022917e320665b02ce4\"\n}\n"
        },
        {
            "COMMAND": "[1763010508.012][INFO]: [5fbd50b274790022917e320665b02ce4] COMMAND MaximizeWindow {\n}\n",
            "RESPONSE": "[1763010508.057][INFO]: [5fbd50b274790022917e320665b02ce4] RESPONSE MaximizeWindow {\n   \"height\": 832,\n   \"width\": 1552,\n   \"x\": -8,\n   \"y\": -8\n}\n"
        },
        {
            "COMMAND": "[1763010508.062][INFO]: [5fbd50b274790022917e320665b02ce4] COMMAND SetTimeouts {\n   \"implicit\": 30000\n}\n",
            "RESPONSE": null
        },
        {
            "COMMAND": "[1763010508.101][INFO]: [5fbd50b274790022917e320665b02ce4] COMMAND Navigate {\n   \"url\": \"https://www.flipkart.com/\"\n}\n",
            "RESPONSE": "[1763010510.316][INFO]: [5fbd50b274790022917e320665b02ce4] RESPONSE Navigate\n"
        },
        {
            "COMMAND": "[1763010510.340][INFO]: [5fbd50b274790022917e320665b02ce4] COMMAND FindElement {\n   \"using\": \"xpath\",\n   \"value\": \"//input[@name='q']\"\n}\n",
            "RESPONSE": "[1763010510.374][INFO]: [5fbd50b274790022917e320665b02ce4] RESPONSE FindElement {\n   \"element-6066-11e4-a52e-4f735466cecf\": \"f.CF8596CF3572F4D96BD29481BCC04336.d.681B3539927B22B525B70A0130D2F17B.e.101\"\n}\n"
        },
        {
            "COMMAND": "[1763010510.439][INFO]: [5fbd50b274790022917e320665b02ce4] COMMAND ClearElement {\n   \"id\": \"f.CF8596CF3572F4D96BD29481BCC04336.d.681B3539927B22B525B70A0130D2F17B.e.101\"\n}\n",
            "RESPONSE": "[1763010510.531][INFO]: [5fbd50b274790022917e320665b02ce4] RESPONSE ClearElement\n"
        },
        {
            "COMMAND": "[1763010510.539][INFO]: [5fbd50b274790022917e320665b02ce4] COMMAND TypeElement {\n   \"id\": \"f.CF8596CF3572F4D96BD29481BCC04336.d.681B3539927B22B525B70A0130D2F17B.e.101\",\n   \"text\": \"Washing Machine\",\n   \"value\": [ \"W\", \"a\", \"s\", \"h\", \"i\", \"n\", \"g\", \" \", \"M\", \"a\", \"c\", \"h\", \"i\", \"n\", \"e\" ]\n}\n",
            "RESPONSE": "[1763010510.694][INFO]: [5fbd50b274790022917e320665b02ce4] RESPONSE TypeElement\n"
        },
        {
            "COMMAND": "[1763010510.702][INFO]: [5fbd50b274790022917e320665b02ce4] COMMAND TypeElement {\n   \"id\": \"f.CF8596CF3572F4D96BD29481BCC04336.d.681B3539927B22B525B70A0130D2F17B.e.101\",\n   \"text\": \"\u00ee\u20ac\u2021\",\n   \"value\": [ \"\u00ee\u20ac\u2021\" ]\n}\n",
            "RESPONSE": "[1763010512.688][INFO]: [5fbd50b274790022917e320665b02ce4] RESPONSE TypeElement\n"
        },
        {
            "COMMAND": "[1763010515.698][INFO]: [5fbd50b274790022917e320665b02ce4] COMMAND FindElement {\n   \"using\": \"xpath\",\n   \"value\": \"//div[contains(text(), 'Popularity')]\"\n}\n",
            "RESPONSE": "[1763010515.709][INFO]: [5fbd50b274790022917e320665b02ce4] RESPONSE FindElement {\n   \"element-6066-11e4-a52e-4f735466cecf\": \"f.CF8596CF3572F4D96BD29481BCC04336.d.0CAB9B76D0161ED81C2F4B46D108E0CD.e.310\"\n}\n"
        },
        {
            "COMMAND": "[1763010515.727][INFO]: [5fbd50b274790022917e320665b02ce4] COMMAND IsElementEnabled {\n   \"id\": \"f.CF8596CF3572F4D96BD29481BCC04336.d.0CAB9B76D0161ED81C2F4B46D108E0CD.e.310\"\n}\n",
            "RESPONSE": "[1763010515.734][INFO]: [5fbd50b274790022917e320665b02ce4] RESPONSE IsElementEnabled true\n"
        },
        {
            "COMMAND": "[1763010515.736][INFO]: [5fbd50b274790022917e320665b02ce4] COMMAND ClickElement {\n   \"id\": \"f.CF8596CF3572F4D96BD29481BCC04336.d.0CAB9B76D0161ED81C2F4B46D108E0CD.e.310\"\n}\n",
            "RESPONSE": "[1763010515.832][INFO]: [5fbd50b274790022917e320665b02ce4] RESPONSE ClickElement\n"
        },
        {
            "COMMAND": "[1763010515.841][INFO]: [5fbd50b274790022917e320665b02ce4] COMMAND FindElements {\n   \"using\": \"xpath\",\n   \"value\": \"//span[contains(@id, 'productRating')]\"\n}\n",
            "RESPONSE": "[1763010515.853][INFO]: [5fbd50b274790022917e320665b02ce4] RESPONSE FindElements [ {\n   \"element-6066-11e4-a52e-4f735466cecf\": \"f.CF8596CF3572F4D96BD29481BCC04336.d.0CAB9B76D0161ED81C2F4B46D108E0CD.e.312\"\n}, {\n   \"element-6066-11e4-a52e-4f735466cecf\": \"f.CF8596CF3572F4D96BD29481BCC04336.d.0CAB9B76D0161ED81C2F4B46D108E0CD.e.313\"\n}, {\n   \"element-6066-11e4-a52e-4f735466cecf\": \"f.CF8596CF3572F4D96BD29481BCC04336.d.0CAB9B76D0161ED81C2F4B46D108E0CD.e.314\"\n}, {\n   \"element-6066-11e4-a52e-4f735466cecf\": \"f.CF8596CF3572F4D96BD29481BCC04336.d.0CAB9B76D0161ED81C2F4B46D108E0CD.e.315\"\n}, {\n   \"element-6066-11e4-a52e-4f735466cecf\": \"f.CF8596CF3572F4D96BD29481BCC04336.d.0CAB9B76D0161ED81C2F4B46D108E0CD.e.316\"\n}, {\n   \"element-6066-11e4-a52e-4f735466cecf\": \"f.CF8596CF3572F4D96BD29481BCC04336.d.0CAB9B76D0161ED81C2F4B46D108E0CD.e.317\"\n}, {\n   \"element-6066-11e4-a52e-4f735466cecf\": \"f.CF8596CF3572F4D96BD29481BCC04336.d.0CAB9B76D0161ED81C2F4B46D108E0CD.e.318\"\n}, {\n   \"element-6066-11e4-a52e-4f735466cecf\": \"f.CF8596CF3572F4D96BD29481BCC04336.d.0CAB9B76D0161ED81C2F4B46D108E0CD.e.319\"\n}, {\n   \"element-6066-11e4-a52e-4f735466cecf\": \"f.CF8596CF3572F4D96BD29481BCC04336.d.0CAB9B76D0161ED81C2F4B46D108E0CD.e.320\"\n}, {\n   \"element-6066-11e4-a52e-4f735466cecf\": \"f.CF8596CF3572F4D96BD29481BCC04336.d.0CAB9B76D0161ED81C2F4B46D108E0CD.e.321\"\n}, {\n   \"element-6066-11e4-a52e-4f735466cecf\": \"f.CF8596CF3572F4D96BD29481BCC04336.d.0CAB9B76D0161ED81C2F4B46D108E0CD.e.322\"\n}, {\n   \"element-6066-11e4-a52e-4f735466cecf\": \"f.CF8596CF3572F4D96BD29481BCC04336.d.0CAB9B76D0161ED81C2F4B46D108E0CD.e.323\"\n}, {\n   \"element-6066-11e4-a52e-4f735466cecf\": \"f.CF8596CF3572F4D96BD29481BCC04336.d.0CAB9B76D0161ED81C2F4B46D108E0CD.e.324\"\n}, {\n   \"element-6066-11e4-a52e-4f735466cecf\": \"f.CF8596CF3572F4D96BD29481BCC04336.d.0CAB9B76D0161ED81C2F4B46D108E0CD.e.325\"\n}, {\n   \"element-6066-11e4-a52e-4f735466cecf\": \"f.CF8596CF3572F4D96BD29481BCC04336.d.0CAB9B76D0161ED81C2F4B46D108E0CD.e.326\"\n}, {\n   \"element-6066-11e4-a52e-4f735466cecf\": \"f.CF8596CF3572F4D96BD29481BCC04336.d.0CAB9B76D0161ED81C2F4B46D108E0CD.e.327\"\n}, {\n   \"element-6066-11e4-a52e-4f735466cecf\": \"f.CF8596CF3572F4D96BD29481BCC04336.d.0CAB9B76D0161ED81C2F4B46D108E0CD.e.328\"\n}, {\n   \"element-6066-11e4-a52e-4f735466cecf\": \"f.CF8596CF3572F4D96BD29481BCC04336.d.0CAB9B76D0161ED81C2F4B46D108E0CD.e.329\"\n}, {\n   \"element-6066-11e4-a52e-4f735466cecf\": \"f.CF8596CF3572F4D96BD29481BCC04336.d.0CAB9B76D0161ED81C2F4B46D108E0CD.e.330\"\n}, \"...\" ]\n"
        },
        {
            "COMMAND": "[1763010515.857][INFO]: [5fbd50b274790022917e320665b02ce4] COMMAND GetElementText {\n   \"id\": \"f.CF8596CF3572F4D96BD29481BCC04336.d.0CAB9B76D0161ED81C2F4B46D108E0CD.e.312\"\n}\n",
            "RESPONSE": "[1763010515.870][INFO]: [5fbd50b274790022917e320665b02ce4] RESPONSE GetElementText \"4.4\"\n"
        },
        {
            "COMMAND": "[1763010515.872][INFO]: [5fbd50b274790022917e320665b02ce4] COMMAND GetElementText {\n   \"id\": \"f.CF8596CF3572F4D96BD29481BCC04336.d.0CAB9B76D0161ED81C2F4B46D108E0CD.e.313\"\n}\n",
            "RESPONSE": "[1763010515.880][INFO]: [5fbd50b274790022917e320665b02ce4] RESPONSE GetElementText \"4.3\"\n"
        },
        {
            "COMMAND": "[1763010515.882][INFO]: [5fbd50b274790022917e320665b02ce4] COMMAND GetElementText {\n   \"id\": \"f.CF8596CF3572F4D96BD29481BCC04336.d.0CAB9B76D0161ED81C2F4B46D108E0CD.e.314\"\n}\n",
            "RESPONSE": "[1763010515.891][INFO]: [5fbd50b274790022917e320665b02ce4] RESPONSE GetElementText \"4.2\"\n"
        },
        {
            "COMMAND": "[1763010515.893][INFO]: [5fbd50b274790022917e320665b02ce4] COMMAND GetElementText {\n   \"id\": \"f.CF8596CF3572F4D96BD29481BCC04336.d.0CAB9B76D0161ED81C2F4B46D108E0CD.e.315\"\n}\n",
            "RESPONSE": "[1763010515.901][INFO]: [5fbd50b274790022917e320665b02ce4] RESPONSE GetElementText \"4.2\"\n"
        },
        {
            "COMMAND": "[1763010515.903][INFO]: [5fbd50b274790022917e320665b02ce4] COMMAND GetElementText {\n   \"id\": \"f.CF8596CF3572F4D96BD29481BCC04336.d.0CAB9B76D0161ED81C2F4B46D108E0CD.e.316\"\n}\n",
            "RESPONSE": "[1763010515.910][INFO]: [5fbd50b274790022917e320665b02ce4] RESPONSE GetElementText \"4.3\"\n"
        },
        {
            "COMMAND": "[1763010515.912][INFO]: [5fbd50b274790022917e320665b02ce4] COMMAND GetElementText {\n   \"id\": \"f.CF8596CF3572F4D96BD29481BCC04336.d.0CAB9B76D0161ED81C2F4B46D108E0CD.e.317\"\n}\n",
            "RESPONSE": "[1763010515.920][INFO]: [5fbd50b274790022917e320665b02ce4] RESPONSE GetElementText \"4.1\"\n"
        },
        {
            "COMMAND": "[1763010515.922][INFO]: [5fbd50b274790022917e320665b02ce4] COMMAND GetElementText {\n   \"id\": \"f.CF8596CF3572F4D96BD29481BCC04336.d.0CAB9B76D0161ED81C2F4B46D108E0CD.e.318\"\n}\n",
            "RESPONSE": "[1763010515.931][INFO]: [5fbd50b274790022917e320665b02ce4] RESPONSE GetElementText \"4.4\"\n"
        },
        {
            "COMMAND": "[1763010515.933][INFO]: [5fbd50b274790022917e320665b02ce4] COMMAND GetElementText {\n   \"id\": \"f.CF8596CF3572F4D96BD29481BCC04336.d.0CAB9B76D0161ED81C2F4B46D108E0CD.e.319\"\n}\n",
            "RESPONSE": "[1763010515.941][INFO]: [5fbd50b274790022917e320665b02ce4] RESPONSE GetElementText \"4.3\"\n"
        },
        {
            "COMMAND": "[1763010515.943][INFO]: [5fbd50b274790022917e320665b02ce4] COMMAND GetElementText {\n   \"id\": \"f.CF8596CF3572F4D96BD29481BCC04336.d.0CAB9B76D0161ED81C2F4B46D108E0CD.e.320\"\n}\n",
            "RESPONSE": "[1763010515.951][INFO]: [5fbd50b274790022917e320665b02ce4] RESPONSE GetElementText \"4.3\"\n"
        },
        {
            "COMMAND": "[1763010515.954][INFO]: [5fbd50b274790022917e320665b02ce4] COMMAND GetElementText {\n   \"id\": \"f.CF8596CF3572F4D96BD29481BCC04336.d.0CAB9B76D0161ED81C2F4B46D108E0CD.e.321\"\n}\n",
            "RESPONSE": "[1763010515.963][INFO]: [5fbd50b274790022917e320665b02ce4] RESPONSE GetElementText \"4.3\"\n"
        },
        {
            "COMMAND": "[1763010515.965][INFO]: [5fbd50b274790022917e320665b02ce4] COMMAND GetElementText {\n   \"id\": \"f.CF8596CF3572F4D96BD29481BCC04336.d.0CAB9B76D0161ED81C2F4B46D108E0CD.e.322\"\n}\n",
            "RESPONSE": "[1763010515.972][INFO]: [5fbd50b274790022917e320665b02ce4] RESPONSE GetElementText \"4.3\"\n"
        },
        {
            "COMMAND": "[1763010515.975][INFO]: [5fbd50b274790022917e320665b02ce4] COMMAND GetElementText {\n   \"id\": \"f.CF8596CF3572F4D96BD29481BCC04336.d.0CAB9B76D0161ED81C2F4B46D108E0CD.e.323\"\n}\n",
            "RESPONSE": "[1763010515.982][INFO]: [5fbd50b274790022917e320665b02ce4] RESPONSE GetElementText \"4.4\"\n"
        },
        {
            "COMMAND": "[1763010515.984][INFO]: [5fbd50b274790022917e320665b02ce4] COMMAND GetElementText {\n   \"id\": \"f.CF8596CF3572F4D96BD29481BCC04336.d.0CAB9B76D0161ED81C2F4B46D108E0CD.e.324\"\n}\n",
            "RESPONSE": "[1763010515.992][INFO]: [5fbd50b274790022917e320665b02ce4] RESPONSE GetElementText \"4.3\"\n"
        },
        {
            "COMMAND": "[1763010515.994][INFO]: [5fbd50b274790022917e320665b02ce4] COMMAND GetElementText {\n   \"id\": \"f.CF8596CF3572F4D96BD29481BCC04336.d.0CAB9B76D0161ED81C2F4B46D108E0CD.e.325\"\n}\n",
            "RESPONSE": "[1763010516.004][INFO]: [5fbd50b274790022917e320665b02ce4] RESPONSE GetElementText \"4\"\n"
        },
        {
            "COMMAND": "[1763010516.006][INFO]: [5fbd50b274790022917e320665b02ce4] COMMAND GetElementText {\n   \"id\": \"f.CF8596CF3572F4D96BD29481BCC04336.d.0CAB9B76D0161ED81C2F4B46D108E0CD.e.326\"\n}\n",
            "RESPONSE": "[1763010516.015][INFO]: [5fbd50b274790022917e320665b02ce4] RESPONSE GetElementText \"4.4\"\n"
        },
        {
            "COMMAND": "[1763010516.017][INFO]: [5fbd50b274790022917e320665b02ce4] COMMAND GetElementText {\n   \"id\": \"f.CF8596CF3572F4D96BD29481BCC04336.d.0CAB9B76D0161ED81C2F4B46D108E0CD.e.327\"\n}\n",
            "RESPONSE": "[1763010516.025][INFO]: [5fbd50b274790022917e320665b02ce4] RESPONSE GetElementText \"4.1\"\n"
        },
        {
            "COMMAND": "[1763010516.027][INFO]: [5fbd50b274790022917e320665b02ce4] COMMAND GetElementText {\n   \"id\": \"f.CF8596CF3572F4D96BD29481BCC04336.d.0CAB9B76D0161ED81C2F4B46D108E0CD.e.328\"\n}\n",
            "RESPONSE": "[1763010516.034][INFO]: [5fbd50b274790022917e320665b02ce4] RESPONSE GetElementText \"4.3\"\n"
        },
        {
            "COMMAND": "[1763010516.036][INFO]: [5fbd50b274790022917e320665b02ce4] COMMAND GetElementText {\n   \"id\": \"f.CF8596CF3572F4D96BD29481BCC04336.d.0CAB9B76D0161ED81C2F4B46D108E0CD.e.329\"\n}\n",
            "RESPONSE": "[1763010516.044][INFO]: [5fbd50b274790022917e320665b02ce4] RESPONSE GetElementText \"4.3\"\n"
        },
        {
            "COMMAND": "[1763010516.046][INFO]: [5fbd50b274790022917e320665b02ce4] COMMAND GetElementText {\n   \"id\": \"f.CF8596CF3572F4D96BD29481BCC04336.d.0CAB9B76D0161ED81C2F4B46D108E0CD.e.330\"\n}\n",
            "RESPONSE": "[1763010516.053][INFO]: [5fbd50b274790022917e320665b02ce4] RESPONSE GetElementText \"4.3\"\n"
        },
        {
            "COMMAND": "[1763010516.056][INFO]: [5fbd50b274790022917e320665b02ce4] COMMAND GetElementText {\n   \"id\": \"f.CF8596CF3572F4D96BD29481BCC04336.d.0CAB9B76D0161ED81C2F4B46D108E0CD.e.331\"\n}\n",
            "RESPONSE": "[1763010516.064][INFO]: [5fbd50b274790022917e320665b02ce4] RESPONSE GetElementText \"4\"\n"
        },
        {
            "COMMAND": "[1763010516.069][INFO]: [5fbd50b274790022917e320665b02ce4] COMMAND GetElementText {\n   \"id\": \"f.CF8596CF3572F4D96BD29481BCC04336.d.0CAB9B76D0161ED81C2F4B46D108E0CD.e.332\"\n}\n",
            "RESPONSE": "[1763010516.078][INFO]: [5fbd50b274790022917e320665b02ce4] RESPONSE GetElementText \"4.4\"\n"
        },
        {
            "COMMAND": "[1763010516.079][INFO]: [5fbd50b274790022917e320665b02ce4] COMMAND GetElementText {\n   \"id\": \"f.CF8596CF3572F4D96BD29481BCC04336.d.0CAB9B76D0161ED81C2F4B46D108E0CD.e.333\"\n}\n",
            "RESPONSE": "[1763010516.087][INFO]: [5fbd50b274790022917e320665b02ce4] RESPONSE GetElementText \"4.3\"\n"
        },
        {
            "COMMAND": "[1763010516.089][INFO]: [5fbd50b274790022917e320665b02ce4] COMMAND GetElementText {\n   \"id\": \"f.CF8596CF3572F4D96BD29481BCC04336.d.0CAB9B76D0161ED81C2F4B46D108E0CD.e.334\"\n}\n",
            "RESPONSE": "[1763010516.097][INFO]: [5fbd50b274790022917e320665b02ce4] RESPONSE GetElementText \"4.3\"\n"
        },
        {
            "COMMAND": "[1763010516.099][INFO]: [5fbd50b274790022917e320665b02ce4] COMMAND GetElementText {\n   \"id\": \"f.CF8596CF3572F4D96BD29481BCC04336.d.0CAB9B76D0161ED81C2F4B46D108E0CD.e.335\"\n}\n",
            "RESPONSE": "[1763010516.106][INFO]: [5fbd50b274790022917e320665b02ce4] RESPONSE GetElementText \"4.1\"\n"
        },
        {
            "COMMAND": "[1763010516.119][INFO]: [5fbd50b274790022917e320665b02ce4] COMMAND Navigate {\n   \"url\": \"https://www.flipkart.com/\"\n}\n",
            "RESPONSE": "[1763010517.714][INFO]: [5fbd50b274790022917e320665b02ce4] RESPONSE Navigate\n"
        },
        {
            "COMMAND": "[1763010520.719][INFO]: [5fbd50b274790022917e320665b02ce4] COMMAND FindElement {\n   \"using\": \"xpath\",\n   \"value\": \"//span[contains(@class, '_30X89F')]\"\n}\n",
            "RESPONSE": "[1763010550.743][INFO]: [5fbd50b274790022917e320665b02ce4] RESPONSE FindElement ERROR no such element: Unable to locate element: {\"method\":\"xpath\",\"selector\":\"//span[contains(@class, '_30X89F')]\"}\n  (Session info: chrome=142.0.7444.135)\n"
        },
        {
            "COMMAND": "[1763010553.754][INFO]: [5fbd50b274790022917e320665b02ce4] COMMAND FindElement {\n   \"using\": \"xpath\",\n   \"value\": \"//input[contains(@class, 'Pke_EE')]\"\n}\n",
            "RESPONSE": "[1763010553.763][INFO]: [5fbd50b274790022917e320665b02ce4] RESPONSE FindElement {\n   \"element-6066-11e4-a52e-4f735466cecf\": \"f.CF8596CF3572F4D96BD29481BCC04336.d.04110CFC3E5FB35A90CD0FCE287371BF.e.342\"\n}\n"
        },
        {
            "COMMAND": "[1763010553.782][INFO]: [5fbd50b274790022917e320665b02ce4] COMMAND ClearElement {\n   \"id\": \"f.CF8596CF3572F4D96BD29481BCC04336.d.04110CFC3E5FB35A90CD0FCE287371BF.e.342\"\n}\n",
            "RESPONSE": "[1763010553.830][INFO]: [5fbd50b274790022917e320665b02ce4] RESPONSE ClearElement\n"
        },
        {
            "COMMAND": "[1763010553.837][INFO]: [5fbd50b274790022917e320665b02ce4] COMMAND TypeElement {\n   \"id\": \"f.CF8596CF3572F4D96BD29481BCC04336.d.04110CFC3E5FB35A90CD0FCE287371BF.e.342\",\n   \"text\": \"iPhone\",\n   \"value\": [ \"i\", \"P\", \"h\", \"o\", \"n\", \"e\" ]\n}\n",
            "RESPONSE": "[1763010553.936][INFO]: [5fbd50b274790022917e320665b02ce4] RESPONSE TypeElement\n"
        },
        {
            "COMMAND": "[1763010553.942][INFO]: [5fbd50b274790022917e320665b02ce4] COMMAND TypeElement {\n   \"id\": \"f.CF8596CF3572F4D96BD29481BCC04336.d.04110CFC3E5FB35A90CD0FCE287371BF.e.342\",\n   \"text\": \"\u00ee\u20ac\u2021\",\n   \"value\": [ \"\u00ee\u20ac\u2021\" ]\n}\n",
            "RESPONSE": "[1763010555.610][INFO]: [5fbd50b274790022917e320665b02ce4] RESPONSE TypeElement\n"
        },
        {
            "COMMAND": "[1763010558.614][INFO]: [5fbd50b274790022917e320665b02ce4] COMMAND FindElements {\n   \"using\": \"xpath\",\n   \"value\": \"//div[contains(@class, 'UkUFwK')]\"\n}\n",
            "RESPONSE": "[1763010558.625][INFO]: [5fbd50b274790022917e320665b02ce4] RESPONSE FindElements [ {\n   \"element-6066-11e4-a52e-4f735466cecf\": \"f.CF8596CF3572F4D96BD29481BCC04336.d.88A41554255941AD35E55A69AE4C9C86.e.587\"\n}, {\n   \"element-6066-11e4-a52e-4f735466cecf\": \"f.CF8596CF3572F4D96BD29481BCC04336.d.88A41554255941AD35E55A69AE4C9C86.e.588\"\n}, {\n   \"element-6066-11e4-a52e-4f735466cecf\": \"f.CF8596CF3572F4D96BD29481BCC04336.d.88A41554255941AD35E55A69AE4C9C86.e.589\"\n}, {\n   \"element-6066-11e4-a52e-4f735466cecf\": \"f.CF8596CF3572F4D96BD29481BCC04336.d.88A41554255941AD35E55A69AE4C9C86.e.590\"\n}, {\n   \"element-6066-11e4-a52e-4f735466cecf\": \"f.CF8596CF3572F4D96BD29481BCC04336.d.88A41554255941AD35E55A69AE4C9C86.e.591\"\n} ]\n"
        },
        {
            "COMMAND": "[1763010558.627][INFO]: [5fbd50b274790022917e320665b02ce4] COMMAND GetElementText {\n   \"id\": \"f.CF8596CF3572F4D96BD29481BCC04336.d.88A41554255941AD35E55A69AE4C9C86.e.587\"\n}\n",
            "RESPONSE": "[1763010558.639][INFO]: [5fbd50b274790022917e320665b02ce4] RESPONSE GetElementText \"15% off\"\n"
        },
        {
            "COMMAND": "[1763010558.640][INFO]: [5fbd50b274790022917e320665b02ce4] COMMAND GetElementText {\n   \"id\": \"f.CF8596CF3572F4D96BD29481BCC04336.d.88A41554255941AD35E55A69AE4C9C86.e.588\"\n}\n",
            "RESPONSE": "[1763010558.648][INFO]: [5fbd50b274790022917e320665b02ce4] RESPONSE GetElementText \"3% off\"\n"
        },
        {
            "COMMAND": "[1763010558.650][INFO]: [5fbd50b274790022917e320665b02ce4] COMMAND GetElementText {\n   \"id\": \"f.CF8596CF3572F4D96BD29481BCC04336.d.88A41554255941AD35E55A69AE4C9C86.e.589\"\n}\n",
            "RESPONSE": "[1763010558.656][INFO]: [5fbd50b274790022917e320665b02ce4] RESPONSE GetElementText \"15% off\"\n"
        },
        {
            "COMMAND": "[1763010558.658][INFO]: [5fbd50b274790022917e320665b02ce4] COMMAND GetElementText {\n   \"id\": \"f.CF8596CF3572F4D96BD29481BCC04336.d.88A41554255941AD35E55A69AE4C9C86.e.590\"\n}\n",
            "RESPONSE": "[1763010558.666][INFO]: [5fbd50b274790022917e320665b02ce4] RESPONSE GetElementText \"3% off\"\n"
        },
        {
            "COMMAND": "[1763010558.668][INFO]: [5fbd50b274790022917e320665b02ce4] COMMAND GetElementText {\n   \"id\": \"f.CF8596CF3572F4D96BD29481BCC04336.d.88A41554255941AD35E55A69AE4C9C86.e.591\"\n}\n",
            "RESPONSE": "[1763010558.675][INFO]: [5fbd50b274790022917e320665b02ce4] RESPONSE GetElementText \"15% off\"\n"
        },
        {
            "COMMAND": "[1763010558.678][INFO]: [5fbd50b274790022917e320665b02ce4] COMMAND Navigate {\n   \"url\": \"https://www.flipkart.com/\"\n}\n",
            "RESPONSE": "[1763010561.662][INFO]: [5fbd50b274790022917e320665b02ce4] RESPONSE Navigate\n"
        },
        {
            "COMMAND": "[1763010561.666][INFO]: [5fbd50b274790022917e320665b02ce4] COMMAND FindElement {\n   \"using\": \"xpath\",\n   \"value\": \"//span[text()='\u00e2\u0153\u2022']\"\n}\n",
            "RESPONSE": "[1763010561.694][INFO]: [5fbd50b274790022917e320665b02ce4] RESPONSE FindElement {\n   \"element-6066-11e4-a52e-4f735466cecf\": \"f.CF8596CF3572F4D96BD29481BCC04336.d.8A371E39718FBE8AB116D0DECB61822A.e.638\"\n}\n"
        },
        {
            "COMMAND": "[1763010561.725][INFO]: [5fbd50b274790022917e320665b02ce4] COMMAND ClickElement {\n   \"id\": \"f.CF8596CF3572F4D96BD29481BCC04336.d.8A371E39718FBE8AB116D0DECB61822A.e.638\"\n}\n",
            "RESPONSE": "[1763010561.848][INFO]: [5fbd50b274790022917e320665b02ce4] RESPONSE ClickElement\n"
        },
        {
            "COMMAND": "[1763010561.853][INFO]: [5fbd50b274790022917e320665b02ce4] COMMAND FindElement {\n   \"using\": \"css selector\",\n   \"value\": \"*[name='q']\"\n}\n",
            "RESPONSE": "[1763010561.868][INFO]: [5fbd50b274790022917e320665b02ce4] RESPONSE FindElement {\n   \"element-6066-11e4-a52e-4f735466cecf\": \"f.CF8596CF3572F4D96BD29481BCC04336.d.8A371E39718FBE8AB116D0DECB61822A.e.625\"\n}\n"
        },
        {
            "COMMAND": "[1763010561.912][INFO]: [5fbd50b274790022917e320665b02ce4] COMMAND ClearElement {\n   \"id\": \"f.CF8596CF3572F4D96BD29481BCC04336.d.8A371E39718FBE8AB116D0DECB61822A.e.625\"\n}\n",
            "RESPONSE": "[1763010562.018][INFO]: [5fbd50b274790022917e320665b02ce4] RESPONSE ClearElement\n"
        },
        {
            "COMMAND": "[1763010562.020][INFO]: [5fbd50b274790022917e320665b02ce4] COMMAND TypeElement {\n   \"id\": \"f.CF8596CF3572F4D96BD29481BCC04336.d.8A371E39718FBE8AB116D0DECB61822A.e.625\",\n   \"text\": \"Coffee Mug\",\n   \"value\": [ \"C\", \"o\", \"f\", \"f\", \"e\", \"e\", \" \", \"M\", \"u\", \"g\" ]\n}\n",
            "RESPONSE": "[1763010562.084][INFO]: [5fbd50b274790022917e320665b02ce4] RESPONSE TypeElement\n"
        },
        {
            "COMMAND": "[1763010562.086][INFO]: [5fbd50b274790022917e320665b02ce4] COMMAND TypeElement {\n   \"id\": \"f.CF8596CF3572F4D96BD29481BCC04336.d.8A371E39718FBE8AB116D0DECB61822A.e.625\",\n   \"text\": \"\u00ee\u20ac\u2021\",\n   \"value\": [ \"\u00ee\u20ac\u2021\" ]\n}\n",
            "RESPONSE": "[1763010564.958][INFO]: [5fbd50b274790022917e320665b02ce4] RESPONSE TypeElement\n"
        },
        {
            "COMMAND": "[1763010564.962][INFO]: [5fbd50b274790022917e320665b02ce4] COMMAND FindElement {\n   \"using\": \"css selector\",\n   \"value\": \"*[name='q']\"\n}\n",
            "RESPONSE": "[1763010564.979][INFO]: [5fbd50b274790022917e320665b02ce4] RESPONSE FindElement {\n   \"element-6066-11e4-a52e-4f735466cecf\": \"f.CF8596CF3572F4D96BD29481BCC04336.d.776697E7CEAFCCCBAB9B35277F6E0A77.e.705\"\n}\n"
        },
        {
            "COMMAND": "[1763010564.982][INFO]: [5fbd50b274790022917e320665b02ce4] COMMAND TypeElement {\n   \"id\": \"f.CF8596CF3572F4D96BD29481BCC04336.d.776697E7CEAFCCCBAB9B35277F6E0A77.e.705\",\n   \"text\": \"\u00ee\u20ac\u2021\",\n   \"value\": [ \"\u00ee\u20ac\u2021\" ]\n}\n",
            "RESPONSE": "[1763010565.086][INFO]: [5fbd50b274790022917e320665b02ce4] RESPONSE TypeElement\n"
        },
        {
            "COMMAND": "[1763010567.592][INFO]: [5fbd50b274790022917e320665b02ce4] COMMAND FindElement {\n   \"using\": \"xpath\",\n   \"value\": \"//div[text()='4\u00e2\u02dc\u2026 & above']\"\n}\n",
            "RESPONSE": "[1763010567.604][INFO]: [5fbd50b274790022917e320665b02ce4] RESPONSE FindElement {\n   \"element-6066-11e4-a52e-4f735466cecf\": \"f.CF8596CF3572F4D96BD29481BCC04336.d.776697E7CEAFCCCBAB9B35277F6E0A77.e.719\"\n}\n"
        },
        {
            "COMMAND": "[1763010567.615][INFO]: [5fbd50b274790022917e320665b02ce4] COMMAND IsElementEnabled {\n   \"id\": \"f.CF8596CF3572F4D96BD29481BCC04336.d.776697E7CEAFCCCBAB9B35277F6E0A77.e.719\"\n}\n",
            "RESPONSE": "[1763010567.623][INFO]: [5fbd50b274790022917e320665b02ce4] RESPONSE IsElementEnabled true\n"
        },
        {
            "COMMAND": "[1763010567.625][INFO]: [5fbd50b274790022917e320665b02ce4] COMMAND ClickElement {\n   \"id\": \"f.CF8596CF3572F4D96BD29481BCC04336.d.776697E7CEAFCCCBAB9B35277F6E0A77.e.719\"\n}\n",
            "RESPONSE": "[1763010567.723][INFO]: [5fbd50b274790022917e320665b02ce4] RESPONSE ClickElement\n"
        },
        {
            "COMMAND": "[1763010570.726][INFO]: [5fbd50b274790022917e320665b02ce4] COMMAND FindElement {\n   \"using\": \"xpath\",\n   \"value\": \"//div[@data-id]\"\n}\n",
            "RESPONSE": "[1763010570.737][INFO]: [5fbd50b274790022917e320665b02ce4] RESPONSE FindElement {\n   \"element-6066-11e4-a52e-4f735466cecf\": \"f.CF8596CF3572F4D96BD29481BCC04336.d.776697E7CEAFCCCBAB9B35277F6E0A77.e.757\"\n}\n"
        },
        {
            "COMMAND": "[1763010570.748][INFO]: [5fbd50b274790022917e320665b02ce4] COMMAND FindElements {\n   \"using\": \"xpath\",\n   \"value\": \"//div[@data-id]\"\n}\n",
            "RESPONSE": "[1763010570.759][INFO]: [5fbd50b274790022917e320665b02ce4] RESPONSE FindElements [ {\n   \"element-6066-11e4-a52e-4f735466cecf\": \"f.CF8596CF3572F4D96BD29481BCC04336.d.776697E7CEAFCCCBAB9B35277F6E0A77.e.757\"\n}, {\n   \"element-6066-11e4-a52e-4f735466cecf\": \"f.CF8596CF3572F4D96BD29481BCC04336.d.776697E7CEAFCCCBAB9B35277F6E0A77.e.758\"\n}, {\n   \"element-6066-11e4-a52e-4f735466cecf\": \"f.CF8596CF3572F4D96BD29481BCC04336.d.776697E7CEAFCCCBAB9B35277F6E0A77.e.759\"\n}, {\n   \"element-6066-11e4-a52e-4f735466cecf\": \"f.CF8596CF3572F4D96BD29481BCC04336.d.776697E7CEAFCCCBAB9B35277F6E0A77.e.760\"\n}, {\n   \"element-6066-11e4-a52e-4f735466cecf\": \"f.CF8596CF3572F4D96BD29481BCC04336.d.776697E7CEAFCCCBAB9B35277F6E0A77.e.761\"\n}, {\n   \"element-6066-11e4-a52e-4f735466cecf\": \"f.CF8596CF3572F4D96BD29481BCC04336.d.776697E7CEAFCCCBAB9B35277F6E0A77.e.762\"\n}, {\n   \"element-6066-11e4-a52e-4f735466cecf\": \"f.CF8596CF3572F4D96BD29481BCC04336.d.776697E7CEAFCCCBAB9B35277F6E0A77.e.763\"\n}, {\n   \"element-6066-11e4-a52e-4f735466cecf\": \"f.CF8596CF3572F4D96BD29481BCC04336.d.776697E7CEAFCCCBAB9B35277F6E0A77.e.764\"\n}, {\n   \"element-6066-11e4-a52e-4f735466cecf\": \"f.CF8596CF3572F4D96BD29481BCC04336.d.776697E7CEAFCCCBAB9B35277F6E0A77.e.765\"\n}, {\n   \"element-6066-11e4-a52e-4f735466cecf\": \"f.CF8596CF3572F4D96BD29481BCC04336.d.776697E7CEAFCCCBAB9B35277F6E0A77.e.766\"\n}, {\n   \"element-6066-11e4-a52e-4f735466cecf\": \"f.CF8596CF3572F4D96BD29481BCC04336.d.776697E7CEAFCCCBAB9B35277F6E0A77.e.767\"\n}, {\n   \"element-6066-11e4-a52e-4f735466cecf\": \"f.CF8596CF3572F4D96BD29481BCC04336.d.776697E7CEAFCCCBAB9B35277F6E0A77.e.768\"\n}, {\n   \"element-6066-11e4-a52e-4f735466cecf\": \"f.CF8596CF3572F4D96BD29481BCC04336.d.776697E7CEAFCCCBAB9B35277F6E0A77.e.769\"\n}, {\n   \"element-6066-11e4-a52e-4f735466cecf\": \"f.CF8596CF3572F4D96BD29481BCC04336.d.776697E7CEAFCCCBAB9B35277F6E0A77.e.770\"\n}, {\n   \"element-6066-11e4-a52e-4f735466cecf\": \"f.CF8596CF3572F4D96BD29481BCC04336.d.776697E7CEAFCCCBAB9B35277F6E0A77.e.771\"\n}, {\n   \"element-6066-11e4-a52e-4f735466cecf\": \"f.CF8596CF3572F4D96BD29481BCC04336.d.776697E7CEAFCCCBAB9B35277F6E0A77.e.772\"\n}, {\n   \"element-6066-11e4-a52e-4f735466cecf\": \"f.CF8596CF3572F4D96BD29481BCC04336.d.776697E7CEAFCCCBAB9B35277F6E0A77.e.773\"\n}, {\n   \"element-6066-11e4-a52e-4f735466cecf\": \"f.CF8596CF3572F4D96BD29481BCC04336.d.776697E7CEAFCCCBAB9B35277F6E0A77.e.774\"\n}, {\n   \"element-6066-11e4-a52e-4f735466cecf\": \"f.CF8596CF3572F4D96BD29481BCC04336.d.776697E7CEAFCCCBAB9B35277F6E0A77.e.775\"\n}, \"...\" ]\n"
        },
        {
            "COMMAND": "[1763010570.763][INFO]: [5fbd50b274790022917e320665b02ce4] COMMAND FindChildElement {\n   \"id\": \"f.CF8596CF3572F4D96BD29481BCC04336.d.776697E7CEAFCCCBAB9B35277F6E0A77.e.757\",\n   \"using\": \"xpath\",\n   \"value\": \".//a[contains(@class,'s1Q9rs')]\"\n}\n",
            "RESPONSE": "[1763010600.776][INFO]: [5fbd50b274790022917e320665b02ce4] RESPONSE FindChildElement ERROR no such element: Unable to locate element: {\"method\":\"xpath\",\"selector\":\".//a[contains(@class,'s1Q9rs')]\"}\n  (Session info: chrome=142.0.7444.135)\n"
        },
        {
            "COMMAND": "[1763010600.780][INFO]: [5fbd50b274790022917e320665b02ce4] COMMAND FindChildElement {\n   \"id\": \"f.CF8596CF3572F4D96BD29481BCC04336.d.776697E7CEAFCCCBAB9B35277F6E0A77.e.757\",\n   \"using\": \"xpath\",\n   \"value\": \".//a[contains(@class,'IRpwTa')]\"\n}\n",
            "RESPONSE": "[1763010630.806][INFO]: [5fbd50b274790022917e320665b02ce4] RESPONSE FindChildElement ERROR no such element: Unable to locate element: {\"method\":\"xpath\",\"selector\":\".//a[contains(@class,'IRpwTa')]\"}\n  (Session info: chrome=142.0.7444.135)\n"
        },
        {
            "COMMAND": "[1763010630.809][INFO]: [5fbd50b274790022917e320665b02ce4] COMMAND FindChildElement {\n   \"id\": \"f.CF8596CF3572F4D96BD29481BCC04336.d.776697E7CEAFCCCBAB9B35277F6E0A77.e.757\",\n   \"using\": \"xpath\",\n   \"value\": \".//a[contains(@class,'V0OXxd')]\"\n}\n",
            "RESPONSE": "[1763010660.831][INFO]: [5fbd50b274790022917e320665b02ce4] RESPONSE FindChildElement ERROR no such element: Unable to locate element: {\"method\":\"xpath\",\"selector\":\".//a[contains(@class,'V0OXxd')]\"}\n  (Session info: chrome=142.0.7444.135)\n"
        },
        {
            "COMMAND": "[1763010660.835][INFO]: [5fbd50b274790022917e320665b02ce4] COMMAND FindChildElement {\n   \"id\": \"f.CF8596CF3572F4D96BD29481BCC04336.d.776697E7CEAFCCCBAB9B35277F6E0A77.e.758\",\n   \"using\": \"xpath\",\n   \"value\": \".//a[contains(@class,'s1Q9rs')]\"\n}\n",
            "RESPONSE": "[1763010690.840][INFO]: [5fbd50b274790022917e320665b02ce4] RESPONSE FindChildElement ERROR no such element: Unable to locate element: {\"method\":\"xpath\",\"selector\":\".//a[contains(@class,'s1Q9rs')]\"}\n  (Session info: chrome=142.0.7444.135)\n"
        },
        {
            "COMMAND": "[1763010690.846][INFO]: [5fbd50b274790022917e320665b02ce4] COMMAND FindChildElement {\n   \"id\": \"f.CF8596CF3572F4D96BD29481BCC04336.d.776697E7CEAFCCCBAB9B35277F6E0A77.e.758\",\n   \"using\": \"xpath\",\n   \"value\": \".//a[contains(@class,'IRpwTa')]\"\n}\n",
            "RESPONSE": "[1763010720.876][INFO]: [5fbd50b274790022917e320665b02ce4] RESPONSE FindChildElement ERROR no such element: Unable to locate element: {\"method\":\"xpath\",\"selector\":\".//a[contains(@class,'IRpwTa')]\"}\n  (Session info: chrome=142.0.7444.135)\n"
        },
        {
            "COMMAND": "[1763010720.880][INFO]: [5fbd50b274790022917e320665b02ce4] COMMAND FindChildElement {\n   \"id\": \"f.CF8596CF3572F4D96BD29481BCC04336.d.776697E7CEAFCCCBAB9B35277F6E0A77.e.758\",\n   \"using\": \"xpath\",\n   \"value\": \".//a[contains(@class,'V0OXxd')]\"\n}\n",
            "RESPONSE": "[1763010750.934][INFO]: [5fbd50b274790022917e320665b02ce4] RESPONSE FindChildElement ERROR no such element: Unable to locate element: {\"method\":\"xpath\",\"selector\":\".//a[contains(@class,'V0OXxd')]\"}\n  (Session info: chrome=142.0.7444.135)\n"
        },
        {
            "COMMAND": "[1763010750.937][INFO]: [5fbd50b274790022917e320665b02ce4] COMMAND FindChildElement {\n   \"id\": \"f.CF8596CF3572F4D96BD29481BCC04336.d.776697E7CEAFCCCBAB9B35277F6E0A77.e.759\",\n   \"using\": \"xpath\",\n   \"value\": \".//a[contains(@class,'s1Q9rs')]\"\n}\n",
            "RESPONSE": "[1763010780.948][INFO]: [5fbd50b274790022917e320665b02ce4] RESPONSE FindChildElement ERROR no such element: Unable to locate element: {\"method\":\"xpath\",\"selector\":\".//a[contains(@class,'s1Q9rs')]\"}\n  (Session info: chrome=142.0.7444.135)\n"
        },
        {
            "COMMAND": "[1763010780.951][INFO]: [5fbd50b274790022917e320665b02ce4] COMMAND FindChildElement {\n   \"id\": \"f.CF8596CF3572F4D96BD29481BCC04336.d.776697E7CEAFCCCBAB9B35277F6E0A77.e.759\",\n   \"using\": \"xpath\",\n   \"value\": \".//a[contains(@class,'IRpwTa')]\"\n}\n",
            "RESPONSE": "[1763010810.956][INFO]: [5fbd50b274790022917e320665b02ce4] RESPONSE FindChildElement ERROR no such element: Unable to locate element: {\"method\":\"xpath\",\"selector\":\".//a[contains(@class,'IRpwTa')]\"}\n  (Session info: chrome=142.0.7444.135)\n"
        },
        {
            "COMMAND": "[1763010810.960][INFO]: [5fbd50b274790022917e320665b02ce4] COMMAND FindChildElement {\n   \"id\": \"f.CF8596CF3572F4D96BD29481BCC04336.d.776697E7CEAFCCCBAB9B35277F6E0A77.e.759\",\n   \"using\": \"xpath\",\n   \"value\": \".//a[contains(@class,'V0OXxd')]\"\n}\n",
            "RESPONSE": "[1763010841.018][INFO]: [5fbd50b274790022917e320665b02ce4] RESPONSE FindChildElement ERROR no such element: Unable to locate element: {\"method\":\"xpath\",\"selector\":\".//a[contains(@class,'V0OXxd')]\"}\n  (Session info: chrome=142.0.7444.135)\n"
        },
        {
            "COMMAND": "[1763010841.022][INFO]: [5fbd50b274790022917e320665b02ce4] COMMAND FindChildElement {\n   \"id\": \"f.CF8596CF3572F4D96BD29481BCC04336.d.776697E7CEAFCCCBAB9B35277F6E0A77.e.760\",\n   \"using\": \"xpath\",\n   \"value\": \".//a[contains(@class,'s1Q9rs')]\"\n}\n",
            "RESPONSE": "[1763010871.074][INFO]: [5fbd50b274790022917e320665b02ce4] RESPONSE FindChildElement ERROR no such element: Unable to locate element: {\"method\":\"xpath\",\"selector\":\".//a[contains(@class,'s1Q9rs')]\"}\n  (Session info: chrome=142.0.7444.135)\n"
        },
        {
            "COMMAND": "[1763010871.077][INFO]: [5fbd50b274790022917e320665b02ce4] COMMAND FindChildElement {\n   \"id\": \"f.CF8596CF3572F4D96BD29481BCC04336.d.776697E7CEAFCCCBAB9B35277F6E0A77.e.760\",\n   \"using\": \"xpath\",\n   \"value\": \".//a[contains(@class,'IRpwTa')]\"\n}\n",
            "RESPONSE": "[1763010901.121][INFO]: [5fbd50b274790022917e320665b02ce4] RESPONSE FindChildElement ERROR no such element: Unable to locate element: {\"method\":\"xpath\",\"selector\":\".//a[contains(@class,'IRpwTa')]\"}\n  (Session info: chrome=142.0.7444.135)\n"
        },
        {
            "COMMAND": "[1763010901.124][INFO]: [5fbd50b274790022917e320665b02ce4] COMMAND FindChildElement {\n   \"id\": \"f.CF8596CF3572F4D96BD29481BCC04336.d.776697E7CEAFCCCBAB9B35277F6E0A77.e.760\",\n   \"using\": \"xpath\",\n   \"value\": \".//a[contains(@class,'V0OXxd')]\"\n}\n",
            "RESPONSE": "[1763010931.128][INFO]: [5fbd50b274790022917e320665b02ce4] RESPONSE FindChildElement ERROR no such element: Unable to locate element: {\"method\":\"xpath\",\"selector\":\".//a[contains(@class,'V0OXxd')]\"}\n  (Session info: chrome=142.0.7444.135)\n"
        },
        {
            "COMMAND": "[1763010931.132][INFO]: [5fbd50b274790022917e320665b02ce4] COMMAND FindChildElement {\n   \"id\": \"f.CF8596CF3572F4D96BD29481BCC04336.d.776697E7CEAFCCCBAB9B35277F6E0A77.e.761\",\n   \"using\": \"xpath\",\n   \"value\": \".//a[contains(@class,'s1Q9rs')]\"\n}\n",
            "RESPONSE": "[1763010961.195][INFO]: [5fbd50b274790022917e320665b02ce4] RESPONSE FindChildElement ERROR no such element: Unable to locate element: {\"method\":\"xpath\",\"selector\":\".//a[contains(@class,'s1Q9rs')]\"}\n  (Session info: chrome=142.0.7444.135)\n"
        },
        {
            "COMMAND": "[1763010961.198][INFO]: [5fbd50b274790022917e320665b02ce4] COMMAND FindChildElement {\n   \"id\": \"f.CF8596CF3572F4D96BD29481BCC04336.d.776697E7CEAFCCCBAB9B35277F6E0A77.e.761\",\n   \"using\": \"xpath\",\n   \"value\": \".//a[contains(@class,'IRpwTa')]\"\n}\n",
            "RESPONSE": "[1763010991.252][INFO]: [5fbd50b274790022917e320665b02ce4] RESPONSE FindChildElement ERROR no such element: Unable to locate element: {\"method\":\"xpath\",\"selector\":\".//a[contains(@class,'IRpwTa')]\"}\n  (Session info: chrome=142.0.7444.135)\n"
        },
        {
            "COMMAND": "[1763010991.256][INFO]: [5fbd50b274790022917e320665b02ce4] COMMAND FindChildElement {\n   \"id\": \"f.CF8596CF3572F4D96BD29481BCC04336.d.776697E7CEAFCCCBAB9B35277F6E0A77.e.761\",\n   \"using\": \"xpath\",\n   \"value\": \".//a[contains(@class,'V0OXxd')]\"\n}\n",
            "RESPONSE": "[1763011021.297][INFO]: [5fbd50b274790022917e320665b02ce4] RESPONSE FindChildElement ERROR no such element: Unable to locate element: {\"method\":\"xpath\",\"selector\":\".//a[contains(@class,'V0OXxd')]\"}\n  (Session info: chrome=142.0.7444.135)\n"
        },
        {
            "COMMAND": "[1763011021.300][INFO]: [5fbd50b274790022917e320665b02ce4] COMMAND FindChildElement {\n   \"id\": \"f.CF8596CF3572F4D96BD29481BCC04336.d.776697E7CEAFCCCBAB9B35277F6E0A77.e.762\",\n   \"using\": \"xpath\",\n   \"value\": \".//a[contains(@class,'s1Q9rs')]\"\n}\n",
            "RESPONSE": "[1763011051.316][INFO]: [5fbd50b274790022917e320665b02ce4] RESPONSE FindChildElement ERROR no such element: Unable to locate element: {\"method\":\"xpath\",\"selector\":\".//a[contains(@class,'s1Q9rs')]\"}\n  (Session info: chrome=142.0.7444.135)\n"
        },
        {
            "COMMAND": "[1763011051.319][INFO]: [5fbd50b274790022917e320665b02ce4] COMMAND FindChildElement {\n   \"id\": \"f.CF8596CF3572F4D96BD29481BCC04336.d.776697E7CEAFCCCBAB9B35277F6E0A77.e.762\",\n   \"using\": \"xpath\",\n   \"value\": \".//a[contains(@class,'IRpwTa')]\"\n}\n",
            "RESPONSE": "[1763011081.354][INFO]: [5fbd50b274790022917e320665b02ce4] RESPONSE FindChildElement ERROR no such element: Unable to locate element: {\"method\":\"xpath\",\"selector\":\".//a[contains(@class,'IRpwTa')]\"}\n  (Session info: chrome=142.0.7444.135)\n"
        },
        {
            "COMMAND": "[1763011081.357][INFO]: [5fbd50b274790022917e320665b02ce4] COMMAND FindChildElement {\n   \"id\": \"f.CF8596CF3572F4D96BD29481BCC04336.d.776697E7CEAFCCCBAB9B35277F6E0A77.e.762\",\n   \"using\": \"xpath\",\n   \"value\": \".//a[contains(@class,'V0OXxd')]\"\n}\n",
            "RESPONSE": "[1763011111.410][INFO]: [5fbd50b274790022917e320665b02ce4] RESPONSE FindChildElement ERROR no such element: Unable to locate element: {\"method\":\"xpath\",\"selector\":\".//a[contains(@class,'V0OXxd')]\"}\n  (Session info: chrome=142.0.7444.135)\n"
        },
        {
            "COMMAND": "[1763011111.414][INFO]: [5fbd50b274790022917e320665b02ce4] COMMAND FindChildElement {\n   \"id\": \"f.CF8596CF3572F4D96BD29481BCC04336.d.776697E7CEAFCCCBAB9B35277F6E0A77.e.763\",\n   \"using\": \"xpath\",\n   \"value\": \".//a[contains(@class,'s1Q9rs')]\"\n}\n",
            "RESPONSE": "[1763011141.455][INFO]: [5fbd50b274790022917e320665b02ce4] RESPONSE FindChildElement ERROR no such element: Unable to locate element: {\"method\":\"xpath\",\"selector\":\".//a[contains(@class,'s1Q9rs')]\"}\n  (Session info: chrome=142.0.7444.135)\n"
        },
        {
            "COMMAND": "[1763011141.458][INFO]: [5fbd50b274790022917e320665b02ce4] COMMAND FindChildElement {\n   \"id\": \"f.CF8596CF3572F4D96BD29481BCC04336.d.776697E7CEAFCCCBAB9B35277F6E0A77.e.763\",\n   \"using\": \"xpath\",\n   \"value\": \".//a[contains(@class,'IRpwTa')]\"\n}\n",
            "RESPONSE": "[1763011171.484][INFO]: [5fbd50b274790022917e320665b02ce4] RESPONSE FindChildElement ERROR no such element: Unable to locate element: {\"method\":\"xpath\",\"selector\":\".//a[contains(@class,'IRpwTa')]\"}\n  (Session info: chrome=142.0.7444.135)\n"
        },
        {
            "COMMAND": "[1763011171.487][INFO]: [5fbd50b274790022917e320665b02ce4] COMMAND FindChildElement {\n   \"id\": \"f.CF8596CF3572F4D96BD29481BCC04336.d.776697E7CEAFCCCBAB9B35277F6E0A77.e.763\",\n   \"using\": \"xpath\",\n   \"value\": \".//a[contains(@class,'V0OXxd')]\"\n}\n",
            "RESPONSE": "[1763011201.525][INFO]: [5fbd50b274790022917e320665b02ce4] RESPONSE FindChildElement ERROR no such element: Unable to locate element: {\"method\":\"xpath\",\"selector\":\".//a[contains(@class,'V0OXxd')]\"}\n  (Session info: chrome=142.0.7444.135)\n"
        },
        {
            "COMMAND": "[1763011201.529][INFO]: [5fbd50b274790022917e320665b02ce4] COMMAND FindChildElement {\n   \"id\": \"f.CF8596CF3572F4D96BD29481BCC04336.d.776697E7CEAFCCCBAB9B35277F6E0A77.e.764\",\n   \"using\": \"xpath\",\n   \"value\": \".//a[contains(@class,'s1Q9rs')]\"\n}\n",
            "RESPONSE": "[1763011231.573][INFO]: [5fbd50b274790022917e320665b02ce4] RESPONSE FindChildElement ERROR no such element: Unable to locate element: {\"method\":\"xpath\",\"selector\":\".//a[contains(@class,'s1Q9rs')]\"}\n  (Session info: chrome=142.0.7444.135)\n"
        },
        {
            "COMMAND": "[1763011231.576][INFO]: [5fbd50b274790022917e320665b02ce4] COMMAND FindChildElement {\n   \"id\": \"f.CF8596CF3572F4D96BD29481BCC04336.d.776697E7CEAFCCCBAB9B35277F6E0A77.e.764\",\n   \"using\": \"xpath\",\n   \"value\": \".//a[contains(@class,'IRpwTa')]\"\n}\n",
            "RESPONSE": "[1763011261.596][INFO]: [5fbd50b274790022917e320665b02ce4] RESPONSE FindChildElement ERROR no such element: Unable to locate element: {\"method\":\"xpath\",\"selector\":\".//a[contains(@class,'IRpwTa')]\"}\n  (Session info: chrome=142.0.7444.135)\n"
        },
        {
            "COMMAND": "[1763011261.599][INFO]: [5fbd50b274790022917e320665b02ce4] COMMAND FindChildElement {\n   \"id\": \"f.CF8596CF3572F4D96BD29481BCC04336.d.776697E7CEAFCCCBAB9B35277F6E0A77.e.764\",\n   \"using\": \"xpath\",\n   \"value\": \".//a[contains(@class,'V0OXxd')]\"\n}\n",
            "RESPONSE": "[1763011291.623][INFO]: [5fbd50b274790022917e320665b02ce4] RESPONSE FindChildElement ERROR no such element: Unable to locate element: {\"method\":\"xpath\",\"selector\":\".//a[contains(@class,'V0OXxd')]\"}\n  (Session info: chrome=142.0.7444.135)\n"
        },
        {
            "COMMAND": "[1763011291.626][INFO]: [5fbd50b274790022917e320665b02ce4] COMMAND FindChildElement {\n   \"id\": \"f.CF8596CF3572F4D96BD29481BCC04336.d.776697E7CEAFCCCBAB9B35277F6E0A77.e.765\",\n   \"using\": \"xpath\",\n   \"value\": \".//a[contains(@class,'s1Q9rs')]\"\n}\n",
            "RESPONSE": "[1763011321.635][INFO]: [5fbd50b274790022917e320665b02ce4] RESPONSE FindChildElement ERROR no such element: Unable to locate element: {\"method\":\"xpath\",\"selector\":\".//a[contains(@class,'s1Q9rs')]\"}\n  (Session info: chrome=142.0.7444.135)\n"
        },
        {
            "COMMAND": "[1763011321.638][INFO]: [5fbd50b274790022917e320665b02ce4] COMMAND FindChildElement {\n   \"id\": \"f.CF8596CF3572F4D96BD29481BCC04336.d.776697E7CEAFCCCBAB9B35277F6E0A77.e.765\",\n   \"using\": \"xpath\",\n   \"value\": \".//a[contains(@class,'IRpwTa')]\"\n}\n",
            "RESPONSE": "[1763011351.692][INFO]: [5fbd50b274790022917e320665b02ce4] RESPONSE FindChildElement ERROR no such element: Unable to locate element: {\"method\":\"xpath\",\"selector\":\".//a[contains(@class,'IRpwTa')]\"}\n  (Session info: chrome=142.0.7444.135)\n"
        },
        {
            "COMMAND": "[1763011351.695][INFO]: [5fbd50b274790022917e320665b02ce4] COMMAND FindChildElement {\n   \"id\": \"f.CF8596CF3572F4D96BD29481BCC04336.d.776697E7CEAFCCCBAB9B35277F6E0A77.e.765\",\n   \"using\": \"xpath\",\n   \"value\": \".//a[contains(@class,'V0OXxd')]\"\n}\n",
            "RESPONSE": "[1763011381.748][INFO]: [5fbd50b274790022917e320665b02ce4] RESPONSE FindChildElement ERROR no such element: Unable to locate element: {\"method\":\"xpath\",\"selector\":\".//a[contains(@class,'V0OXxd')]\"}\n  (Session info: chrome=142.0.7444.135)\n"
        },
        {
            "COMMAND": "[1763011381.751][INFO]: [5fbd50b274790022917e320665b02ce4] COMMAND FindChildElement {\n   \"id\": \"f.CF8596CF3572F4D96BD29481BCC04336.d.776697E7CEAFCCCBAB9B35277F6E0A77.e.766\",\n   \"using\": \"xpath\",\n   \"value\": \".//a[contains(@class,'s1Q9rs')]\"\n}\n",
            "RESPONSE": "[1763011411.792][INFO]: [5fbd50b274790022917e320665b02ce4] RESPONSE FindChildElement ERROR no such element: Unable to locate element: {\"method\":\"xpath\",\"selector\":\".//a[contains(@class,'s1Q9rs')]\"}\n  (Session info: chrome=142.0.7444.135)\n"
        },
        {
            "COMMAND": "[1763011411.795][INFO]: [5fbd50b274790022917e320665b02ce4] COMMAND FindChildElement {\n   \"id\": \"f.CF8596CF3572F4D96BD29481BCC04336.d.776697E7CEAFCCCBAB9B35277F6E0A77.e.766\",\n   \"using\": \"xpath\",\n   \"value\": \".//a[contains(@class,'IRpwTa')]\"\n}\n",
            "RESPONSE": "[1763011441.846][INFO]: [5fbd50b274790022917e320665b02ce4] RESPONSE FindChildElement ERROR no such element: Unable to locate element: {\"method\":\"xpath\",\"selector\":\".//a[contains(@class,'IRpwTa')]\"}\n  (Session info: chrome=142.0.7444.135)\n"
        },
        {
            "COMMAND": "[1763011441.849][INFO]: [5fbd50b274790022917e320665b02ce4] COMMAND FindChildElement {\n   \"id\": \"f.CF8596CF3572F4D96BD29481BCC04336.d.776697E7CEAFCCCBAB9B35277F6E0A77.e.766\",\n   \"using\": \"xpath\",\n   \"value\": \".//a[contains(@class,'V0OXxd')]\"\n}\n",
            "RESPONSE": "[1763011471.875][INFO]: [5fbd50b274790022917e320665b02ce4] RESPONSE FindChildElement ERROR no such element: Unable to locate element: {\"method\":\"xpath\",\"selector\":\".//a[contains(@class,'V0OXxd')]\"}\n  (Session info: chrome=142.0.7444.135)\n"
        },
        {
            "COMMAND": "[1763011471.880][INFO]: [5fbd50b274790022917e320665b02ce4] COMMAND FindChildElement {\n   \"id\": \"f.CF8596CF3572F4D96BD29481BCC04336.d.776697E7CEAFCCCBAB9B35277F6E0A77.e.767\",\n   \"using\": \"xpath\",\n   \"value\": \".//a[contains(@class,'s1Q9rs')]\"\n}\n",
            "RESPONSE": "[1763011501.926][INFO]: [5fbd50b274790022917e320665b02ce4] RESPONSE FindChildElement ERROR no such element: Unable to locate element: {\"method\":\"xpath\",\"selector\":\".//a[contains(@class,'s1Q9rs')]\"}\n  (Session info: chrome=142.0.7444.135)\n"
        },
        {
            "COMMAND": "[1763011501.929][INFO]: [5fbd50b274790022917e320665b02ce4] COMMAND FindChildElement {\n   \"id\": \"f.CF8596CF3572F4D96BD29481BCC04336.d.776697E7CEAFCCCBAB9B35277F6E0A77.e.767\",\n   \"using\": \"xpath\",\n   \"value\": \".//a[contains(@class,'IRpwTa')]\"\n}\n",
            "RESPONSE": "[1763011531.944][INFO]: [5fbd50b274790022917e320665b02ce4] RESPONSE FindChildElement ERROR no such element: Unable to locate element: {\"method\":\"xpath\",\"selector\":\".//a[contains(@class,'IRpwTa')]\"}\n  (Session info: chrome=142.0.7444.135)\n"
        },
        {
            "COMMAND": "[1763011531.948][INFO]: [5fbd50b274790022917e320665b02ce4] COMMAND FindChildElement {\n   \"id\": \"f.CF8596CF3572F4D96BD29481BCC04336.d.776697E7CEAFCCCBAB9B35277F6E0A77.e.767\",\n   \"using\": \"xpath\",\n   \"value\": \".//a[contains(@class,'V0OXxd')]\"\n}\n",
            "RESPONSE": "[1763011561.981][INFO]: [5fbd50b274790022917e320665b02ce4] RESPONSE FindChildElement ERROR no such element: Unable to locate element: {\"method\":\"xpath\",\"selector\":\".//a[contains(@class,'V0OXxd')]\"}\n  (Session info: chrome=142.0.7444.135)\n"
        },
        {
            "COMMAND": "[1763011562.084][INFO]: [5fbd50b274790022917e320665b02ce4] COMMAND FindChildElement {\n   \"id\": \"f.CF8596CF3572F4D96BD29481BCC04336.d.776697E7CEAFCCCBAB9B35277F6E0A77.e.768\",\n   \"using\": \"xpath\",\n   \"value\": \".//a[contains(@class,'s1Q9rs')]\"\n}\n",
            "RESPONSE": "[1763011592.091][INFO]: [5fbd50b274790022917e320665b02ce4] RESPONSE FindChildElement ERROR no such element: Unable to locate element: {\"method\":\"xpath\",\"selector\":\".//a[contains(@class,'s1Q9rs')]\"}\n  (Session info: chrome=142.0.7444.135)\n"
        },
        {
            "COMMAND": "[1763011592.094][INFO]: [5fbd50b274790022917e320665b02ce4] COMMAND FindChildElement {\n   \"id\": \"f.CF8596CF3572F4D96BD29481BCC04336.d.776697E7CEAFCCCBAB9B35277F6E0A77.e.768\",\n   \"using\": \"xpath\",\n   \"value\": \".//a[contains(@class,'IRpwTa')]\"\n}\n",
            "RESPONSE": "[1763011622.102][INFO]: [5fbd50b274790022917e320665b02ce4] RESPONSE FindChildElement ERROR no such element: Unable to locate element: {\"method\":\"xpath\",\"selector\":\".//a[contains(@class,'IRpwTa')]\"}\n  (Session info: chrome=142.0.7444.135)\n"
        },
        {
            "COMMAND": "[1763011622.105][INFO]: [5fbd50b274790022917e320665b02ce4] COMMAND FindChildElement {\n   \"id\": \"f.CF8596CF3572F4D96BD29481BCC04336.d.776697E7CEAFCCCBAB9B35277F6E0A77.e.768\",\n   \"using\": \"xpath\",\n   \"value\": \".//a[contains(@class,'V0OXxd')]\"\n}\n",
            "RESPONSE": "[1763011652.165][INFO]: [5fbd50b274790022917e320665b02ce4] RESPONSE FindChildElement ERROR no such element: Unable to locate element: {\"method\":\"xpath\",\"selector\":\".//a[contains(@class,'V0OXxd')]\"}\n  (Session info: chrome=142.0.7444.135)\n"
        },
        {
            "COMMAND": "[1763011652.169][INFO]: [5fbd50b274790022917e320665b02ce4] COMMAND FindChildElement {\n   \"id\": \"f.CF8596CF3572F4D96BD29481BCC04336.d.776697E7CEAFCCCBAB9B35277F6E0A77.e.769\",\n   \"using\": \"xpath\",\n   \"value\": \".//a[contains(@class,'s1Q9rs')]\"\n}\n",
            "RESPONSE": "[1763011682.209][INFO]: [5fbd50b274790022917e320665b02ce4] RESPONSE FindChildElement ERROR no such element: Unable to locate element: {\"method\":\"xpath\",\"selector\":\".//a[contains(@class,'s1Q9rs')]\"}\n  (Session info: chrome=142.0.7444.135)\n"
        },
        {
            "COMMAND": "[1763011682.213][INFO]: [5fbd50b274790022917e320665b02ce4] COMMAND FindChildElement {\n   \"id\": \"f.CF8596CF3572F4D96BD29481BCC04336.d.776697E7CEAFCCCBAB9B35277F6E0A77.e.769\",\n   \"using\": \"xpath\",\n   \"value\": \".//a[contains(@class,'IRpwTa')]\"\n}\n",
            "RESPONSE": "[1763011712.233][INFO]: [5fbd50b274790022917e320665b02ce4] RESPONSE FindChildElement ERROR no such element: Unable to locate element: {\"method\":\"xpath\",\"selector\":\".//a[contains(@class,'IRpwTa')]\"}\n  (Session info: chrome=142.0.7444.135)\n"
        },
        {
            "COMMAND": "[1763011712.249][INFO]: [5fbd50b274790022917e320665b02ce4] COMMAND FindChildElement {\n   \"id\": \"f.CF8596CF3572F4D96BD29481BCC04336.d.776697E7CEAFCCCBAB9B35277F6E0A77.e.769\",\n   \"using\": \"xpath\",\n   \"value\": \".//a[contains(@class,'V0OXxd')]\"\n}\n",
            "RESPONSE": "[1763011742.285][INFO]: [5fbd50b274790022917e320665b02ce4] RESPONSE FindChildElement ERROR no such element: Unable to locate element: {\"method\":\"xpath\",\"selector\":\".//a[contains(@class,'V0OXxd')]\"}\n  (Session info: chrome=142.0.7444.135)\n"
        },
        {
            "COMMAND": "[1763011742.398][INFO]: [5fbd50b274790022917e320665b02ce4] COMMAND FindChildElement {\n   \"id\": \"f.CF8596CF3572F4D96BD29481BCC04336.d.776697E7CEAFCCCBAB9B35277F6E0A77.e.770\",\n   \"using\": \"xpath\",\n   \"value\": \".//a[contains(@class,'s1Q9rs')]\"\n}\n",
            "RESPONSE": "[1763011772.447][INFO]: [5fbd50b274790022917e320665b02ce4] RESPONSE FindChildElement ERROR no such element: Unable to locate element: {\"method\":\"xpath\",\"selector\":\".//a[contains(@class,'s1Q9rs')]\"}\n  (Session info: chrome=142.0.7444.135)\n"
        },
        {
            "COMMAND": "[1763011772.555][INFO]: [5fbd50b274790022917e320665b02ce4] COMMAND FindChildElement {\n   \"id\": \"f.CF8596CF3572F4D96BD29481BCC04336.d.776697E7CEAFCCCBAB9B35277F6E0A77.e.770\",\n   \"using\": \"xpath\",\n   \"value\": \".//a[contains(@class,'IRpwTa')]\"\n}\n",
            "RESPONSE": "[1763011802.588][INFO]: [5fbd50b274790022917e320665b02ce4] RESPONSE FindChildElement ERROR no such element: Unable to locate element: {\"method\":\"xpath\",\"selector\":\".//a[contains(@class,'IRpwTa')]\"}\n  (Session info: chrome=142.0.7444.135)\n"
        },
        {
            "COMMAND": "[1763011802.599][INFO]: [5fbd50b274790022917e320665b02ce4] COMMAND FindChildElement {\n   \"id\": \"f.CF8596CF3572F4D96BD29481BCC04336.d.776697E7CEAFCCCBAB9B35277F6E0A77.e.770\",\n   \"using\": \"xpath\",\n   \"value\": \".//a[contains(@class,'V0OXxd')]\"\n}\n",
            "RESPONSE": "[1763011832.637][INFO]: [5fbd50b274790022917e320665b02ce4] RESPONSE FindChildElement ERROR no such element: Unable to locate element: {\"method\":\"xpath\",\"selector\":\".//a[contains(@class,'V0OXxd')]\"}\n  (Session info: chrome=142.0.7444.135)\n"
        },
        {
            "COMMAND": "[1763011832.785][INFO]: [5fbd50b274790022917e320665b02ce4] COMMAND FindChildElement {\n   \"id\": \"f.CF8596CF3572F4D96BD29481BCC04336.d.776697E7CEAFCCCBAB9B35277F6E0A77.e.771\",\n   \"using\": \"xpath\",\n   \"value\": \".//a[contains(@class,'s1Q9rs')]\"\n}\n",
            "RESPONSE": "[1763011862.848][INFO]: [5fbd50b274790022917e320665b02ce4] RESPONSE FindChildElement ERROR no such element: Unable to locate element: {\"method\":\"xpath\",\"selector\":\".//a[contains(@class,'s1Q9rs')]\"}\n  (Session info: chrome=142.0.7444.135)\n"
        },
        {
            "COMMAND": "[1763011862.852][INFO]: [5fbd50b274790022917e320665b02ce4] COMMAND FindChildElement {\n   \"id\": \"f.CF8596CF3572F4D96BD29481BCC04336.d.776697E7CEAFCCCBAB9B35277F6E0A77.e.771\",\n   \"using\": \"xpath\",\n   \"value\": \".//a[contains(@class,'IRpwTa')]\"\n}\n",
            "RESPONSE": "[1763011892.858][INFO]: [5fbd50b274790022917e320665b02ce4] RESPONSE FindChildElement ERROR no such element: Unable to locate element: {\"method\":\"xpath\",\"selector\":\".//a[contains(@class,'IRpwTa')]\"}\n  (Session info: chrome=142.0.7444.135)\n"
        },
        {
            "COMMAND": "[1763011892.861][INFO]: [5fbd50b274790022917e320665b02ce4] COMMAND FindChildElement {\n   \"id\": \"f.CF8596CF3572F4D96BD29481BCC04336.d.776697E7CEAFCCCBAB9B35277F6E0A77.e.771\",\n   \"using\": \"xpath\",\n   \"value\": \".//a[contains(@class,'V0OXxd')]\"\n}\n",
            "RESPONSE": "[1763011922.921][INFO]: [5fbd50b274790022917e320665b02ce4] RESPONSE FindChildElement ERROR no such element: Unable to locate element: {\"method\":\"xpath\",\"selector\":\".//a[contains(@class,'V0OXxd')]\"}\n  (Session info: chrome=142.0.7444.135)\n"
        },
        {
            "COMMAND": "[1763011922.925][INFO]: [5fbd50b274790022917e320665b02ce4] COMMAND FindChildElement {\n   \"id\": \"f.CF8596CF3572F4D96BD29481BCC04336.d.776697E7CEAFCCCBAB9B35277F6E0A77.e.772\",\n   \"using\": \"xpath\",\n   \"value\": \".//a[contains(@class,'s1Q9rs')]\"\n}\n",
            "RESPONSE": "[1763011952.971][INFO]: [5fbd50b274790022917e320665b02ce4] RESPONSE FindChildElement ERROR no such element: Unable to locate element: {\"method\":\"xpath\",\"selector\":\".//a[contains(@class,'s1Q9rs')]\"}\n  (Session info: chrome=142.0.7444.135)\n"
        },
        {
            "COMMAND": "[1763011952.974][INFO]: [5fbd50b274790022917e320665b02ce4] COMMAND FindChildElement {\n   \"id\": \"f.CF8596CF3572F4D96BD29481BCC04336.d.776697E7CEAFCCCBAB9B35277F6E0A77.e.772\",\n   \"using\": \"xpath\",\n   \"value\": \".//a[contains(@class,'IRpwTa')]\"\n}\n",
            "RESPONSE": "[1763011982.985][INFO]: [5fbd50b274790022917e320665b02ce4] RESPONSE FindChildElement ERROR no such element: Unable to locate element: {\"method\":\"xpath\",\"selector\":\".//a[contains(@class,'IRpwTa')]\"}\n  (Session info: chrome=142.0.7444.135)\n"
        },
        {
            "COMMAND": "[1763011982.988][INFO]: [5fbd50b274790022917e320665b02ce4] COMMAND FindChildElement {\n   \"id\": \"f.CF8596CF3572F4D96BD29481BCC04336.d.776697E7CEAFCCCBAB9B35277F6E0A77.e.772\",\n   \"using\": \"xpath\",\n   \"value\": \".//a[contains(@class,'V0OXxd')]\"\n}\n",
            "RESPONSE": "[1763012013.005][INFO]: [5fbd50b274790022917e320665b02ce4] RESPONSE FindChildElement ERROR no such element: Unable to locate element: {\"method\":\"xpath\",\"selector\":\".//a[contains(@class,'V0OXxd')]\"}\n  (Session info: chrome=142.0.7444.135)\n"
        },
        {
            "COMMAND": "[1763012013.104][INFO]: [5fbd50b274790022917e320665b02ce4] COMMAND FindChildElement {\n   \"id\": \"f.CF8596CF3572F4D96BD29481BCC04336.d.776697E7CEAFCCCBAB9B35277F6E0A77.e.773\",\n   \"using\": \"xpath\",\n   \"value\": \".//a[contains(@class,'s1Q9rs')]\"\n}\n",
            "RESPONSE": "[1763012043.148][INFO]: [5fbd50b274790022917e320665b02ce4] RESPONSE FindChildElement ERROR no such element: Unable to locate element: {\"method\":\"xpath\",\"selector\":\".//a[contains(@class,'s1Q9rs')]\"}\n  (Session info: chrome=142.0.7444.135)\n"
        },
        {
            "COMMAND": "[1763012043.151][INFO]: [5fbd50b274790022917e320665b02ce4] COMMAND FindChildElement {\n   \"id\": \"f.CF8596CF3572F4D96BD29481BCC04336.d.776697E7CEAFCCCBAB9B35277F6E0A77.e.773\",\n   \"using\": \"xpath\",\n   \"value\": \".//a[contains(@class,'IRpwTa')]\"\n}\n",
            "RESPONSE": "[1763012073.182][INFO]: [5fbd50b274790022917e320665b02ce4] RESPONSE FindChildElement ERROR no such element: Unable to locate element: {\"method\":\"xpath\",\"selector\":\".//a[contains(@class,'IRpwTa')]\"}\n  (Session info: chrome=142.0.7444.135)\n"
        },
        {
            "COMMAND": "[1763012073.185][INFO]: [5fbd50b274790022917e320665b02ce4] COMMAND FindChildElement {\n   \"id\": \"f.CF8596CF3572F4D96BD29481BCC04336.d.776697E7CEAFCCCBAB9B35277F6E0A77.e.773\",\n   \"using\": \"xpath\",\n   \"value\": \".//a[contains(@class,'V0OXxd')]\"\n}\n",
            "RESPONSE": "[1763012103.191][INFO]: [5fbd50b274790022917e320665b02ce4] RESPONSE FindChildElement ERROR no such element: Unable to locate element: {\"method\":\"xpath\",\"selector\":\".//a[contains(@class,'V0OXxd')]\"}\n  (Session info: chrome=142.0.7444.135)\n"
        },
        {
            "COMMAND": "[1763012103.208][INFO]: [5fbd50b274790022917e320665b02ce4] COMMAND FindChildElement {\n   \"id\": \"f.CF8596CF3572F4D96BD29481BCC04336.d.776697E7CEAFCCCBAB9B35277F6E0A77.e.774\",\n   \"using\": \"xpath\",\n   \"value\": \".//a[contains(@class,'s1Q9rs')]\"\n}\n",
            "RESPONSE": "[1763012133.252][INFO]: [5fbd50b274790022917e320665b02ce4] RESPONSE FindChildElement ERROR no such element: Unable to locate element: {\"method\":\"xpath\",\"selector\":\".//a[contains(@class,'s1Q9rs')]\"}\n  (Session info: chrome=142.0.7444.135)\n"
        },
        {
            "COMMAND": "[1763012133.266][INFO]: [5fbd50b274790022917e320665b02ce4] COMMAND FindChildElement {\n   \"id\": \"f.CF8596CF3572F4D96BD29481BCC04336.d.776697E7CEAFCCCBAB9B35277F6E0A77.e.774\",\n   \"using\": \"xpath\",\n   \"value\": \".//a[contains(@class,'IRpwTa')]\"\n}\n",
            "RESPONSE": "[1763012163.316][INFO]: [5fbd50b274790022917e320665b02ce4] RESPONSE FindChildElement ERROR no such element: Unable to locate element: {\"method\":\"xpath\",\"selector\":\".//a[contains(@class,'IRpwTa')]\"}\n  (Session info: chrome=142.0.7444.135)\n"
        },
        {
            "COMMAND": "[1763012163.334][INFO]: [5fbd50b274790022917e320665b02ce4] COMMAND FindChildElement {\n   \"id\": \"f.CF8596CF3572F4D96BD29481BCC04336.d.776697E7CEAFCCCBAB9B35277F6E0A77.e.774\",\n   \"using\": \"xpath\",\n   \"value\": \".//a[contains(@class,'V0OXxd')]\"\n}\n",
            "RESPONSE": "[1763012193.337][INFO]: [5fbd50b274790022917e320665b02ce4] RESPONSE FindChildElement ERROR no such element: Unable to locate element: {\"method\":\"xpath\",\"selector\":\".//a[contains(@class,'V0OXxd')]\"}\n  (Session info: chrome=142.0.7444.135)\n"
        },
        {
            "COMMAND": "[1763012193.344][INFO]: [5fbd50b274790022917e320665b02ce4] COMMAND FindChildElement {\n   \"id\": \"f.CF8596CF3572F4D96BD29481BCC04336.d.776697E7CEAFCCCBAB9B35277F6E0A77.e.775\",\n   \"using\": \"xpath\",\n   \"value\": \".//a[contains(@class,'s1Q9rs')]\"\n}\n",
            "RESPONSE": "[1763012223.362][INFO]: [5fbd50b274790022917e320665b02ce4] RESPONSE FindChildElement ERROR no such element: Unable to locate element: {\"method\":\"xpath\",\"selector\":\".//a[contains(@class,'s1Q9rs')]\"}\n  (Session info: chrome=142.0.7444.135)\n"
        },
        {
            "COMMAND": "[1763012223.366][INFO]: [5fbd50b274790022917e320665b02ce4] COMMAND FindChildElement {\n   \"id\": \"f.CF8596CF3572F4D96BD29481BCC04336.d.776697E7CEAFCCCBAB9B35277F6E0A77.e.775\",\n   \"using\": \"xpath\",\n   \"value\": \".//a[contains(@class,'IRpwTa')]\"\n}\n",
            "RESPONSE": "[1763012253.384][INFO]: [5fbd50b274790022917e320665b02ce4] RESPONSE FindChildElement ERROR no such element: Unable to locate element: {\"method\":\"xpath\",\"selector\":\".//a[contains(@class,'IRpwTa')]\"}\n  (Session info: chrome=142.0.7444.135)\n"
        },
        {
            "COMMAND": "[1763012253.387][INFO]: [5fbd50b274790022917e320665b02ce4] COMMAND FindChildElement {\n   \"id\": \"f.CF8596CF3572F4D96BD29481BCC04336.d.776697E7CEAFCCCBAB9B35277F6E0A77.e.775\",\n   \"using\": \"xpath\",\n   \"value\": \".//a[contains(@class,'V0OXxd')]\"\n}\n",
            "RESPONSE": "[1763012283.407][INFO]: [5fbd50b274790022917e320665b02ce4] RESPONSE FindChildElement ERROR no such element: Unable to locate element: {\"method\":\"xpath\",\"selector\":\".//a[contains(@class,'V0OXxd')]\"}\n  (Session info: chrome=142.0.7444.135)\n"
        },
        {
            "COMMAND": "[1763012283.419][INFO]: [5fbd50b274790022917e320665b02ce4] COMMAND FindChildElement {\n   \"id\": \"f.CF8596CF3572F4D96BD29481BCC04336.d.776697E7CEAFCCCBAB9B35277F6E0A77.e.776\",\n   \"using\": \"xpath\",\n   \"value\": \".//a[contains(@class,'s1Q9rs')]\"\n}\n",
            "RESPONSE": "[1763012313.469][INFO]: [5fbd50b274790022917e320665b02ce4] RESPONSE FindChildElement ERROR no such element: Unable to locate element: {\"method\":\"xpath\",\"selector\":\".//a[contains(@class,'s1Q9rs')]\"}\n  (Session info: chrome=142.0.7444.135)\n"
        },
        {
            "COMMAND": "[1763012313.473][INFO]: [5fbd50b274790022917e320665b02ce4] COMMAND FindChildElement {\n   \"id\": \"f.CF8596CF3572F4D96BD29481BCC04336.d.776697E7CEAFCCCBAB9B35277F6E0A77.e.776\",\n   \"using\": \"xpath\",\n   \"value\": \".//a[contains(@class,'IRpwTa')]\"\n}\n",
            "RESPONSE": "[1763012343.511][INFO]: [5fbd50b274790022917e320665b02ce4] RESPONSE FindChildElement ERROR no such element: Unable to locate element: {\"method\":\"xpath\",\"selector\":\".//a[contains(@class,'IRpwTa')]\"}\n  (Session info: chrome=142.0.7444.135)\n"
        },
        {
            "COMMAND": "[1763012343.514][INFO]: [5fbd50b274790022917e320665b02ce4] COMMAND FindChildElement {\n   \"id\": \"f.CF8596CF3572F4D96BD29481BCC04336.d.776697E7CEAFCCCBAB9B35277F6E0A77.e.776\",\n   \"using\": \"xpath\",\n   \"value\": \".//a[contains(@class,'V0OXxd')]\"\n}\n",
            "RESPONSE": "[1763012373.540][INFO]: [5fbd50b274790022917e320665b02ce4] RESPONSE FindChildElement ERROR no such element: Unable to locate element: {\"method\":\"xpath\",\"selector\":\".//a[contains(@class,'V0OXxd')]\"}\n  (Session info: chrome=142.0.7444.135)\n"
        },
        {
            "COMMAND": "[1763012373.552][INFO]: [5fbd50b274790022917e320665b02ce4] COMMAND FindChildElement {\n   \"id\": \"f.CF8596CF3572F4D96BD29481BCC04336.d.776697E7CEAFCCCBAB9B35277F6E0A77.e.777\",\n   \"using\": \"xpath\",\n   \"value\": \".//a[contains(@class,'s1Q9rs')]\"\n}\n",
            "RESPONSE": "[1763012403.583][INFO]: [5fbd50b274790022917e320665b02ce4] RESPONSE FindChildElement ERROR no such element: Unable to locate element: {\"method\":\"xpath\",\"selector\":\".//a[contains(@class,'s1Q9rs')]\"}\n  (Session info: chrome=142.0.7444.135)\n"
        },
        {
            "COMMAND": "[1763012403.602][INFO]: [5fbd50b274790022917e320665b02ce4] COMMAND FindChildElement {\n   \"id\": \"f.CF8596CF3572F4D96BD29481BCC04336.d.776697E7CEAFCCCBAB9B35277F6E0A77.e.777\",\n   \"using\": \"xpath\",\n   \"value\": \".//a[contains(@class,'IRpwTa')]\"\n}\n",
            "RESPONSE": "[1763012433.609][INFO]: [5fbd50b274790022917e320665b02ce4] RESPONSE FindChildElement ERROR no such element: Unable to locate element: {\"method\":\"xpath\",\"selector\":\".//a[contains(@class,'IRpwTa')]\"}\n  (Session info: chrome=142.0.7444.135)\n"
        },
        {
            "COMMAND": "[1763012433.640][INFO]: [5fbd50b274790022917e320665b02ce4] COMMAND FindChildElement {\n   \"id\": \"f.CF8596CF3572F4D96BD29481BCC04336.d.776697E7CEAFCCCBAB9B35277F6E0A77.e.777\",\n   \"using\": \"xpath\",\n   \"value\": \".//a[contains(@class,'V0OXxd')]\"\n}\n",
            "RESPONSE": "[1763012463.650][INFO]: [5fbd50b274790022917e320665b02ce4] RESPONSE FindChildElement ERROR no such element: Unable to locate element: {\"method\":\"xpath\",\"selector\":\".//a[contains(@class,'V0OXxd')]\"}\n  (Session info: chrome=142.0.7444.135)\n"
        },
        {
            "COMMAND": "[1763012463.658][INFO]: [5fbd50b274790022917e320665b02ce4] COMMAND FindChildElement {\n   \"id\": \"f.CF8596CF3572F4D96BD29481BCC04336.d.776697E7CEAFCCCBAB9B35277F6E0A77.e.778\",\n   \"using\": \"xpath\",\n   \"value\": \".//a[contains(@class,'s1Q9rs')]\"\n}\n",
            "RESPONSE": "[1763012493.698][INFO]: [5fbd50b274790022917e320665b02ce4] RESPONSE FindChildElement ERROR no such element: Unable to locate element: {\"method\":\"xpath\",\"selector\":\".//a[contains(@class,'s1Q9rs')]\"}\n  (Session info: chrome=142.0.7444.135)\n"
        },
        {
            "COMMAND": "[1763012493.718][INFO]: [5fbd50b274790022917e320665b02ce4] COMMAND FindChildElement {\n   \"id\": \"f.CF8596CF3572F4D96BD29481BCC04336.d.776697E7CEAFCCCBAB9B35277F6E0A77.e.778\",\n   \"using\": \"xpath\",\n   \"value\": \".//a[contains(@class,'IRpwTa')]\"\n}\n",
            "RESPONSE": "[1763012523.735][INFO]: [5fbd50b274790022917e320665b02ce4] RESPONSE FindChildElement ERROR no such element: Unable to locate element: {\"method\":\"xpath\",\"selector\":\".//a[contains(@class,'IRpwTa')]\"}\n  (Session info: chrome=142.0.7444.135)\n"
        },
        {
            "COMMAND": "[1763012523.744][INFO]: [5fbd50b274790022917e320665b02ce4] COMMAND FindChildElement {\n   \"id\": \"f.CF8596CF3572F4D96BD29481BCC04336.d.776697E7CEAFCCCBAB9B35277F6E0A77.e.778\",\n   \"using\": \"xpath\",\n   \"value\": \".//a[contains(@class,'V0OXxd')]\"\n}\n",
            "RESPONSE": "[1763012553.766][INFO]: [5fbd50b274790022917e320665b02ce4] RESPONSE FindChildElement ERROR no such element: Unable to locate element: {\"method\":\"xpath\",\"selector\":\".//a[contains(@class,'V0OXxd')]\"}\n  (Session info: chrome=142.0.7444.135)\n"
        },
        {
            "COMMAND": "[1763012553.789][INFO]: [5fbd50b274790022917e320665b02ce4] COMMAND FindChildElement {\n   \"id\": \"f.CF8596CF3572F4D96BD29481BCC04336.d.776697E7CEAFCCCBAB9B35277F6E0A77.e.779\",\n   \"using\": \"xpath\",\n   \"value\": \".//a[contains(@class,'s1Q9rs')]\"\n}\n",
            "RESPONSE": "[1763012583.831][INFO]: [5fbd50b274790022917e320665b02ce4] RESPONSE FindChildElement ERROR no such element: Unable to locate element: {\"method\":\"xpath\",\"selector\":\".//a[contains(@class,'s1Q9rs')]\"}\n  (Session info: chrome=142.0.7444.135)\n"
        },
        {
            "COMMAND": "[1763012583.962][INFO]: [5fbd50b274790022917e320665b02ce4] COMMAND FindChildElement {\n   \"id\": \"f.CF8596CF3572F4D96BD29481BCC04336.d.776697E7CEAFCCCBAB9B35277F6E0A77.e.779\",\n   \"using\": \"xpath\",\n   \"value\": \".//a[contains(@class,'IRpwTa')]\"\n}\n",
            "RESPONSE": "[1763012614.014][INFO]: [5fbd50b274790022917e320665b02ce4] RESPONSE FindChildElement ERROR no such element: Unable to locate element: {\"method\":\"xpath\",\"selector\":\".//a[contains(@class,'IRpwTa')]\"}\n  (Session info: chrome=142.0.7444.135)\n"
        },
        {
            "COMMAND": "[1763012614.549][INFO]: [5fbd50b274790022917e320665b02ce4] COMMAND FindChildElement {\n   \"id\": \"f.CF8596CF3572F4D96BD29481BCC04336.d.776697E7CEAFCCCBAB9B35277F6E0A77.e.779\",\n   \"using\": \"xpath\",\n   \"value\": \".//a[contains(@class,'V0OXxd')]\"\n}\n",
            "RESPONSE": "[1763012644.584][INFO]: [5fbd50b274790022917e320665b02ce4] RESPONSE FindChildElement ERROR no such element: Unable to locate element: {\"method\":\"xpath\",\"selector\":\".//a[contains(@class,'V0OXxd')]\"}\n  (Session info: chrome=142.0.7444.135)\n"
        },
        {
            "COMMAND": "[1763012644.588][INFO]: [5fbd50b274790022917e320665b02ce4] COMMAND FindChildElement {\n   \"id\": \"f.CF8596CF3572F4D96BD29481BCC04336.d.776697E7CEAFCCCBAB9B35277F6E0A77.e.780\",\n   \"using\": \"xpath\",\n   \"value\": \".//a[contains(@class,'s1Q9rs')]\"\n}\n",
            "RESPONSE": "[1763012674.638][INFO]: [5fbd50b274790022917e320665b02ce4] RESPONSE FindChildElement ERROR no such element: Unable to locate element: {\"method\":\"xpath\",\"selector\":\".//a[contains(@class,'s1Q9rs')]\"}\n  (Session info: chrome=142.0.7444.135)\n"
        },
        {
            "COMMAND": "[1763012674.647][INFO]: [5fbd50b274790022917e320665b02ce4] COMMAND FindChildElement {\n   \"id\": \"f.CF8596CF3572F4D96BD29481BCC04336.d.776697E7CEAFCCCBAB9B35277F6E0A77.e.780\",\n   \"using\": \"xpath\",\n   \"value\": \".//a[contains(@class,'IRpwTa')]\"\n}\n",
            "RESPONSE": "[1763012704.679][INFO]: [5fbd50b274790022917e320665b02ce4] RESPONSE FindChildElement ERROR no such element: Unable to locate element: {\"method\":\"xpath\",\"selector\":\".//a[contains(@class,'IRpwTa')]\"}\n  (Session info: chrome=142.0.7444.135)\n"
        },
        {
            "COMMAND": "[1763012704.689][INFO]: [5fbd50b274790022917e320665b02ce4] COMMAND FindChildElement {\n   \"id\": \"f.CF8596CF3572F4D96BD29481BCC04336.d.776697E7CEAFCCCBAB9B35277F6E0A77.e.780\",\n   \"using\": \"xpath\",\n   \"value\": \".//a[contains(@class,'V0OXxd')]\"\n}\n",
            "RESPONSE": "[1763012734.742][INFO]: [5fbd50b274790022917e320665b02ce4] RESPONSE FindChildElement ERROR no such element: Unable to locate element: {\"method\":\"xpath\",\"selector\":\".//a[contains(@class,'V0OXxd')]\"}\n  (Session info: chrome=142.0.7444.135)\n"
        },
        {
            "COMMAND": "[1763012734.785][INFO]: [5fbd50b274790022917e320665b02ce4] COMMAND FindChildElement {\n   \"id\": \"f.CF8596CF3572F4D96BD29481BCC04336.d.776697E7CEAFCCCBAB9B35277F6E0A77.e.781\",\n   \"using\": \"xpath\",\n   \"value\": \".//a[contains(@class,'s1Q9rs')]\"\n}\n",
            "RESPONSE": "[1763012764.816][INFO]: [5fbd50b274790022917e320665b02ce4] RESPONSE FindChildElement ERROR no such element: Unable to locate element: {\"method\":\"xpath\",\"selector\":\".//a[contains(@class,'s1Q9rs')]\"}\n  (Session info: chrome=142.0.7444.135)\n"
        },
        {
            "COMMAND": "[1763012764.836][INFO]: [5fbd50b274790022917e320665b02ce4] COMMAND FindChildElement {\n   \"id\": \"f.CF8596CF3572F4D96BD29481BCC04336.d.776697E7CEAFCCCBAB9B35277F6E0A77.e.781\",\n   \"using\": \"xpath\",\n   \"value\": \".//a[contains(@class,'IRpwTa')]\"\n}\n",
            "RESPONSE": "[1763012794.885][INFO]: [5fbd50b274790022917e320665b02ce4] RESPONSE FindChildElement ERROR no such element: Unable to locate element: {\"method\":\"xpath\",\"selector\":\".//a[contains(@class,'IRpwTa')]\"}\n  (Session info: chrome=142.0.7444.135)\n"
        },
        {
            "COMMAND": "[1763012794.888][INFO]: [5fbd50b274790022917e320665b02ce4] COMMAND FindChildElement {\n   \"id\": \"f.CF8596CF3572F4D96BD29481BCC04336.d.776697E7CEAFCCCBAB9B35277F6E0A77.e.781\",\n   \"using\": \"xpath\",\n   \"value\": \".//a[contains(@class,'V0OXxd')]\"\n}\n",
            "RESPONSE": "[1763012824.949][INFO]: [5fbd50b274790022917e320665b02ce4] RESPONSE FindChildElement ERROR no such element: Unable to locate element: {\"method\":\"xpath\",\"selector\":\".//a[contains(@class,'V0OXxd')]\"}\n  (Session info: chrome=142.0.7444.135)\n"
        },
        {
            "COMMAND": "[1763012824.953][INFO]: [5fbd50b274790022917e320665b02ce4] COMMAND FindChildElement {\n   \"id\": \"f.CF8596CF3572F4D96BD29481BCC04336.d.776697E7CEAFCCCBAB9B35277F6E0A77.e.782\",\n   \"using\": \"xpath\",\n   \"value\": \".//a[contains(@class,'s1Q9rs')]\"\n}\n",
            "RESPONSE": "[1763012854.965][INFO]: [5fbd50b274790022917e320665b02ce4] RESPONSE FindChildElement ERROR no such element: Unable to locate element: {\"method\":\"xpath\",\"selector\":\".//a[contains(@class,'s1Q9rs')]\"}\n  (Session info: chrome=142.0.7444.135)\n"
        },
        {
            "COMMAND": "[1763012854.968][INFO]: [5fbd50b274790022917e320665b02ce4] COMMAND FindChildElement {\n   \"id\": \"f.CF8596CF3572F4D96BD29481BCC04336.d.776697E7CEAFCCCBAB9B35277F6E0A77.e.782\",\n   \"using\": \"xpath\",\n   \"value\": \".//a[contains(@class,'IRpwTa')]\"\n}\n",
            "RESPONSE": "[1763012885.016][INFO]: [5fbd50b274790022917e320665b02ce4] RESPONSE FindChildElement ERROR no such element: Unable to locate element: {\"method\":\"xpath\",\"selector\":\".//a[contains(@class,'IRpwTa')]\"}\n  (Session info: chrome=142.0.7444.135)\n"
        },
        {
            "COMMAND": "[1763012885.019][INFO]: [5fbd50b274790022917e320665b02ce4] COMMAND FindChildElement {\n   \"id\": \"f.CF8596CF3572F4D96BD29481BCC04336.d.776697E7CEAFCCCBAB9B35277F6E0A77.e.782\",\n   \"using\": \"xpath\",\n   \"value\": \".//a[contains(@class,'V0OXxd')]\"\n}\n",
            "RESPONSE": "[1763012915.025][INFO]: [5fbd50b274790022917e320665b02ce4] RESPONSE FindChildElement ERROR no such element: Unable to locate element: {\"method\":\"xpath\",\"selector\":\".//a[contains(@class,'V0OXxd')]\"}\n  (Session info: chrome=142.0.7444.135)\n"
        },
        {
            "COMMAND": "[1763012915.028][INFO]: [5fbd50b274790022917e320665b02ce4] COMMAND FindChildElement {\n   \"id\": \"f.CF8596CF3572F4D96BD29481BCC04336.d.776697E7CEAFCCCBAB9B35277F6E0A77.e.783\",\n   \"using\": \"xpath\",\n   \"value\": \".//a[contains(@class,'s1Q9rs')]\"\n}\n",
            "RESPONSE": "[1763012945.084][INFO]: [5fbd50b274790022917e320665b02ce4] RESPONSE FindChildElement ERROR no such element: Unable to locate element: {\"method\":\"xpath\",\"selector\":\".//a[contains(@class,'s1Q9rs')]\"}\n  (Session info: chrome=142.0.7444.135)\n"
        },
        {
            "COMMAND": "[1763012945.087][INFO]: [5fbd50b274790022917e320665b02ce4] COMMAND FindChildElement {\n   \"id\": \"f.CF8596CF3572F4D96BD29481BCC04336.d.776697E7CEAFCCCBAB9B35277F6E0A77.e.783\",\n   \"using\": \"xpath\",\n   \"value\": \".//a[contains(@class,'IRpwTa')]\"\n}\n",
            "RESPONSE": "[1763012975.108][INFO]: [5fbd50b274790022917e320665b02ce4] RESPONSE FindChildElement ERROR no such element: Unable to locate element: {\"method\":\"xpath\",\"selector\":\".//a[contains(@class,'IRpwTa')]\"}\n  (Session info: chrome=142.0.7444.135)\n"
        },
        {
            "COMMAND": "[1763012975.126][INFO]: [5fbd50b274790022917e320665b02ce4] COMMAND FindChildElement {\n   \"id\": \"f.CF8596CF3572F4D96BD29481BCC04336.d.776697E7CEAFCCCBAB9B35277F6E0A77.e.783\",\n   \"using\": \"xpath\",\n   \"value\": \".//a[contains(@class,'V0OXxd')]\"\n}\n",
            "RESPONSE": "[1763013005.170][INFO]: [5fbd50b274790022917e320665b02ce4] RESPONSE FindChildElement ERROR no such element: Unable to locate element: {\"method\":\"xpath\",\"selector\":\".//a[contains(@class,'V0OXxd')]\"}\n  (Session info: chrome=142.0.7444.135)\n"
        },
        {
            "COMMAND": "[1763013005.325][INFO]: [5fbd50b274790022917e320665b02ce4] COMMAND FindChildElement {\n   \"id\": \"f.CF8596CF3572F4D96BD29481BCC04336.d.776697E7CEAFCCCBAB9B35277F6E0A77.e.784\",\n   \"using\": \"xpath\",\n   \"value\": \".//a[contains(@class,'s1Q9rs')]\"\n}\n",
            "RESPONSE": "[1763013035.380][INFO]: [5fbd50b274790022917e320665b02ce4] RESPONSE FindChildElement ERROR no such element: Unable to locate element: {\"method\":\"xpath\",\"selector\":\".//a[contains(@class,'s1Q9rs')]\"}\n  (Session info: chrome=142.0.7444.135)\n"
        },
        {
            "COMMAND": "[1763013035.404][INFO]: [5fbd50b274790022917e320665b02ce4] COMMAND FindChildElement {\n   \"id\": \"f.CF8596CF3572F4D96BD29481BCC04336.d.776697E7CEAFCCCBAB9B35277F6E0A77.e.784\",\n   \"using\": \"xpath\",\n   \"value\": \".//a[contains(@class,'IRpwTa')]\"\n}\n",
            "RESPONSE": "[1763013065.417][INFO]: [5fbd50b274790022917e320665b02ce4] RESPONSE FindChildElement ERROR no such element: Unable to locate element: {\"method\":\"xpath\",\"selector\":\".//a[contains(@class,'IRpwTa')]\"}\n  (Session info: chrome=142.0.7444.135)\n"
        },
        {
            "COMMAND": "[1763013065.433][INFO]: [5fbd50b274790022917e320665b02ce4] COMMAND FindChildElement {\n   \"id\": \"f.CF8596CF3572F4D96BD29481BCC04336.d.776697E7CEAFCCCBAB9B35277F6E0A77.e.784\",\n   \"using\": \"xpath\",\n   \"value\": \".//a[contains(@class,'V0OXxd')]\"\n}\n",
            "RESPONSE": "[1763013095.442][INFO]: [5fbd50b274790022917e320665b02ce4] RESPONSE FindChildElement ERROR no such element: Unable to locate element: {\"method\":\"xpath\",\"selector\":\".//a[contains(@class,'V0OXxd')]\"}\n  (Session info: chrome=142.0.7444.135)\n"
        },
        {
            "COMMAND": "[1763013095.453][INFO]: [5fbd50b274790022917e320665b02ce4] COMMAND FindChildElement {\n   \"id\": \"f.CF8596CF3572F4D96BD29481BCC04336.d.776697E7CEAFCCCBAB9B35277F6E0A77.e.785\",\n   \"using\": \"xpath\",\n   \"value\": \".//a[contains(@class,'s1Q9rs')]\"\n}\n",
            "RESPONSE": "[1763013125.499][INFO]: [5fbd50b274790022917e320665b02ce4] RESPONSE FindChildElement ERROR no such element: Unable to locate element: {\"method\":\"xpath\",\"selector\":\".//a[contains(@class,'s1Q9rs')]\"}\n  (Session info: chrome=142.0.7444.135)\n"
        },
        {
            "COMMAND": "[1763013125.661][INFO]: [5fbd50b274790022917e320665b02ce4] COMMAND FindChildElement {\n   \"id\": \"f.CF8596CF3572F4D96BD29481BCC04336.d.776697E7CEAFCCCBAB9B35277F6E0A77.e.785\",\n   \"using\": \"xpath\",\n   \"value\": \".//a[contains(@class,'IRpwTa')]\"\n}\n",
            "RESPONSE": "[1763013155.681][INFO]: [5fbd50b274790022917e320665b02ce4] RESPONSE FindChildElement ERROR no such element: Unable to locate element: {\"method\":\"xpath\",\"selector\":\".//a[contains(@class,'IRpwTa')]\"}\n  (Session info: chrome=142.0.7444.135)\n"
        },
        {
            "COMMAND": "[1763013155.755][INFO]: [5fbd50b274790022917e320665b02ce4] COMMAND FindChildElement {\n   \"id\": \"f.CF8596CF3572F4D96BD29481BCC04336.d.776697E7CEAFCCCBAB9B35277F6E0A77.e.785\",\n   \"using\": \"xpath\",\n   \"value\": \".//a[contains(@class,'V0OXxd')]\"\n}\n",
            "RESPONSE": "[1763013185.798][INFO]: [5fbd50b274790022917e320665b02ce4] RESPONSE FindChildElement ERROR no such element: Unable to locate element: {\"method\":\"xpath\",\"selector\":\".//a[contains(@class,'V0OXxd')]\"}\n  (Session info: chrome=142.0.7444.135)\n"
        },
        {
            "COMMAND": "[1763013185.998][INFO]: [5fbd50b274790022917e320665b02ce4] COMMAND FindChildElement {\n   \"id\": \"f.CF8596CF3572F4D96BD29481BCC04336.d.776697E7CEAFCCCBAB9B35277F6E0A77.e.786\",\n   \"using\": \"xpath\",\n   \"value\": \".//a[contains(@class,'s1Q9rs')]\"\n}\n",
            "RESPONSE": "[1763013216.029][INFO]: [5fbd50b274790022917e320665b02ce4] RESPONSE FindChildElement ERROR no such element: Unable to locate element: {\"method\":\"xpath\",\"selector\":\".//a[contains(@class,'s1Q9rs')]\"}\n  (Session info: chrome=142.0.7444.135)\n"
        },
        {
            "COMMAND": "[1763013216.069][INFO]: [5fbd50b274790022917e320665b02ce4] COMMAND FindChildElement {\n   \"id\": \"f.CF8596CF3572F4D96BD29481BCC04336.d.776697E7CEAFCCCBAB9B35277F6E0A77.e.786\",\n   \"using\": \"xpath\",\n   \"value\": \".//a[contains(@class,'IRpwTa')]\"\n}\n",
            "RESPONSE": "[1763013246.090][INFO]: [5fbd50b274790022917e320665b02ce4] RESPONSE FindChildElement ERROR no such element: Unable to locate element: {\"method\":\"xpath\",\"selector\":\".//a[contains(@class,'IRpwTa')]\"}\n  (Session info: chrome=142.0.7444.135)\n"
        },
        {
            "COMMAND": "[1763013246.094][INFO]: [5fbd50b274790022917e320665b02ce4] COMMAND FindChildElement {\n   \"id\": \"f.CF8596CF3572F4D96BD29481BCC04336.d.776697E7CEAFCCCBAB9B35277F6E0A77.e.786\",\n   \"using\": \"xpath\",\n   \"value\": \".//a[contains(@class,'V0OXxd')]\"\n}\n",
            "RESPONSE": "[1763013276.134][INFO]: [5fbd50b274790022917e320665b02ce4] RESPONSE FindChildElement ERROR no such element: Unable to locate element: {\"method\":\"xpath\",\"selector\":\".//a[contains(@class,'V0OXxd')]\"}\n  (Session info: chrome=142.0.7444.135)\n"
        },
        {
            "COMMAND": "[1763013276.138][INFO]: [5fbd50b274790022917e320665b02ce4] COMMAND FindChildElement {\n   \"id\": \"f.CF8596CF3572F4D96BD29481BCC04336.d.776697E7CEAFCCCBAB9B35277F6E0A77.e.787\",\n   \"using\": \"xpath\",\n   \"value\": \".//a[contains(@class,'s1Q9rs')]\"\n}\n",
            "RESPONSE": "[1763013306.151][INFO]: [5fbd50b274790022917e320665b02ce4] RESPONSE FindChildElement ERROR no such element: Unable to locate element: {\"method\":\"xpath\",\"selector\":\".//a[contains(@class,'s1Q9rs')]\"}\n  (Session info: chrome=142.0.7444.135)\n"
        },
        {
            "COMMAND": "[1763013306.245][INFO]: [5fbd50b274790022917e320665b02ce4] COMMAND FindChildElement {\n   \"id\": \"f.CF8596CF3572F4D96BD29481BCC04336.d.776697E7CEAFCCCBAB9B35277F6E0A77.e.787\",\n   \"using\": \"xpath\",\n   \"value\": \".//a[contains(@class,'IRpwTa')]\"\n}\n",
            "RESPONSE": "[1763013336.277][INFO]: [5fbd50b274790022917e320665b02ce4] RESPONSE FindChildElement ERROR no such element: Unable to locate element: {\"method\":\"xpath\",\"selector\":\".//a[contains(@class,'IRpwTa')]\"}\n  (Session info: chrome=142.0.7444.135)\n"
        },
        {
            "COMMAND": "[1763013336.280][INFO]: [5fbd50b274790022917e320665b02ce4] COMMAND FindChildElement {\n   \"id\": \"f.CF8596CF3572F4D96BD29481BCC04336.d.776697E7CEAFCCCBAB9B35277F6E0A77.e.787\",\n   \"using\": \"xpath\",\n   \"value\": \".//a[contains(@class,'V0OXxd')]\"\n}\n",
            "RESPONSE": "[1763013366.342][INFO]: [5fbd50b274790022917e320665b02ce4] RESPONSE FindChildElement ERROR no such element: Unable to locate element: {\"method\":\"xpath\",\"selector\":\".//a[contains(@class,'V0OXxd')]\"}\n  (Session info: chrome=142.0.7444.135)\n"
        },
        {
            "COMMAND": "[1763013366.552][INFO]: [5fbd50b274790022917e320665b02ce4] COMMAND FindChildElement {\n   \"id\": \"f.CF8596CF3572F4D96BD29481BCC04336.d.776697E7CEAFCCCBAB9B35277F6E0A77.e.788\",\n   \"using\": \"xpath\",\n   \"value\": \".//a[contains(@class,'s1Q9rs')]\"\n}\n",
            "RESPONSE": "[1763013396.581][INFO]: [5fbd50b274790022917e320665b02ce4] RESPONSE FindChildElement ERROR no such element: Unable to locate element: {\"method\":\"xpath\",\"selector\":\".//a[contains(@class,'s1Q9rs')]\"}\n  (Session info: chrome=142.0.7444.135)\n"
        },
        {
            "COMMAND": "[1763013396.679][INFO]: [5fbd50b274790022917e320665b02ce4] COMMAND FindChildElement {\n   \"id\": \"f.CF8596CF3572F4D96BD29481BCC04336.d.776697E7CEAFCCCBAB9B35277F6E0A77.e.788\",\n   \"using\": \"xpath\",\n   \"value\": \".//a[contains(@class,'IRpwTa')]\"\n}\n",
            "RESPONSE": "[1763013426.700][INFO]: [5fbd50b274790022917e320665b02ce4] RESPONSE FindChildElement ERROR no such element: Unable to locate element: {\"method\":\"xpath\",\"selector\":\".//a[contains(@class,'IRpwTa')]\"}\n  (Session info: chrome=142.0.7444.135)\n"
        },
        {
            "COMMAND": "[1763013426.704][INFO]: [5fbd50b274790022917e320665b02ce4] COMMAND FindChildElement {\n   \"id\": \"f.CF8596CF3572F4D96BD29481BCC04336.d.776697E7CEAFCCCBAB9B35277F6E0A77.e.788\",\n   \"using\": \"xpath\",\n   \"value\": \".//a[contains(@class,'V0OXxd')]\"\n}\n",
            "RESPONSE": "[1763013456.745][INFO]: [5fbd50b274790022917e320665b02ce4] RESPONSE FindChildElement ERROR no such element: Unable to locate element: {\"method\":\"xpath\",\"selector\":\".//a[contains(@class,'V0OXxd')]\"}\n  (Session info: chrome=142.0.7444.135)\n"
        },
        {
            "COMMAND": "[1763013456.748][INFO]: [5fbd50b274790022917e320665b02ce4] COMMAND FindChildElement {\n   \"id\": \"f.CF8596CF3572F4D96BD29481BCC04336.d.776697E7CEAFCCCBAB9B35277F6E0A77.e.789\",\n   \"using\": \"xpath\",\n   \"value\": \".//a[contains(@class,'s1Q9rs')]\"\n}\n",
            "RESPONSE": "[1763013486.757][INFO]: [5fbd50b274790022917e320665b02ce4] RESPONSE FindChildElement ERROR no such element: Unable to locate element: {\"method\":\"xpath\",\"selector\":\".//a[contains(@class,'s1Q9rs')]\"}\n  (Session info: chrome=142.0.7444.135)\n"
        },
        {
            "COMMAND": "[1763013486.784][INFO]: [5fbd50b274790022917e320665b02ce4] COMMAND FindChildElement {\n   \"id\": \"f.CF8596CF3572F4D96BD29481BCC04336.d.776697E7CEAFCCCBAB9B35277F6E0A77.e.789\",\n   \"using\": \"xpath\",\n   \"value\": \".//a[contains(@class,'IRpwTa')]\"\n}\n",
            "RESPONSE": "[1763013516.832][INFO]: [5fbd50b274790022917e320665b02ce4] RESPONSE FindChildElement ERROR no such element: Unable to locate element: {\"method\":\"xpath\",\"selector\":\".//a[contains(@class,'IRpwTa')]\"}\n  (Session info: chrome=142.0.7444.135)\n"
        },
        {
            "COMMAND": "[1763013516.861][INFO]: [5fbd50b274790022917e320665b02ce4] COMMAND FindChildElement {\n   \"id\": \"f.CF8596CF3572F4D96BD29481BCC04336.d.776697E7CEAFCCCBAB9B35277F6E0A77.e.789\",\n   \"using\": \"xpath\",\n   \"value\": \".//a[contains(@class,'V0OXxd')]\"\n}\n",
            "RESPONSE": "[1763013546.910][INFO]: [5fbd50b274790022917e320665b02ce4] RESPONSE FindChildElement ERROR no such element: Unable to locate element: {\"method\":\"xpath\",\"selector\":\".//a[contains(@class,'V0OXxd')]\"}\n  (Session info: chrome=142.0.7444.135)\n"
        },
        {
            "COMMAND": "[1763013547.003][INFO]: [5fbd50b274790022917e320665b02ce4] COMMAND FindChildElement {\n   \"id\": \"f.CF8596CF3572F4D96BD29481BCC04336.d.776697E7CEAFCCCBAB9B35277F6E0A77.e.790\",\n   \"using\": \"xpath\",\n   \"value\": \".//a[contains(@class,'s1Q9rs')]\"\n}\n",
            "RESPONSE": "[1763013577.027][INFO]: [5fbd50b274790022917e320665b02ce4] RESPONSE FindChildElement ERROR no such element: Unable to locate element: {\"method\":\"xpath\",\"selector\":\".//a[contains(@class,'s1Q9rs')]\"}\n  (Session info: chrome=142.0.7444.135)\n"
        },
        {
            "COMMAND": "[1763013577.030][INFO]: [5fbd50b274790022917e320665b02ce4] COMMAND FindChildElement {\n   \"id\": \"f.CF8596CF3572F4D96BD29481BCC04336.d.776697E7CEAFCCCBAB9B35277F6E0A77.e.790\",\n   \"using\": \"xpath\",\n   \"value\": \".//a[contains(@class,'IRpwTa')]\"\n}\n",
            "RESPONSE": "[1763013607.038][INFO]: [5fbd50b274790022917e320665b02ce4] RESPONSE FindChildElement ERROR no such element: Unable to locate element: {\"method\":\"xpath\",\"selector\":\".//a[contains(@class,'IRpwTa')]\"}\n  (Session info: chrome=142.0.7444.135)\n"
        },
        {
            "COMMAND": "[1763013607.059][INFO]: [5fbd50b274790022917e320665b02ce4] COMMAND FindChildElement {\n   \"id\": \"f.CF8596CF3572F4D96BD29481BCC04336.d.776697E7CEAFCCCBAB9B35277F6E0A77.e.790\",\n   \"using\": \"xpath\",\n   \"value\": \".//a[contains(@class,'V0OXxd')]\"\n}\n",
            "RESPONSE": "[1763013637.108][INFO]: [5fbd50b274790022917e320665b02ce4] RESPONSE FindChildElement ERROR no such element: Unable to locate element: {\"method\":\"xpath\",\"selector\":\".//a[contains(@class,'V0OXxd')]\"}\n  (Session info: chrome=142.0.7444.135)\n"
        },
        {
            "COMMAND": "[1763013637.112][INFO]: [5fbd50b274790022917e320665b02ce4] COMMAND FindChildElement {\n   \"id\": \"f.CF8596CF3572F4D96BD29481BCC04336.d.776697E7CEAFCCCBAB9B35277F6E0A77.e.791\",\n   \"using\": \"xpath\",\n   \"value\": \".//a[contains(@class,'s1Q9rs')]\"\n}\n",
            "RESPONSE": "[1763013667.151][INFO]: [5fbd50b274790022917e320665b02ce4] RESPONSE FindChildElement ERROR no such element: Unable to locate element: {\"method\":\"xpath\",\"selector\":\".//a[contains(@class,'s1Q9rs')]\"}\n  (Session info: chrome=142.0.7444.135)\n"
        },
        {
            "COMMAND": "[1763013667.173][INFO]: [5fbd50b274790022917e320665b02ce4] COMMAND FindChildElement {\n   \"id\": \"f.CF8596CF3572F4D96BD29481BCC04336.d.776697E7CEAFCCCBAB9B35277F6E0A77.e.791\",\n   \"using\": \"xpath\",\n   \"value\": \".//a[contains(@class,'IRpwTa')]\"\n}\n",
            "RESPONSE": "[1763013697.194][INFO]: [5fbd50b274790022917e320665b02ce4] RESPONSE FindChildElement ERROR no such element: Unable to locate element: {\"method\":\"xpath\",\"selector\":\".//a[contains(@class,'IRpwTa')]\"}\n  (Session info: chrome=142.0.7444.135)\n"
        },
        {
            "COMMAND": "[1763013697.198][INFO]: [5fbd50b274790022917e320665b02ce4] COMMAND FindChildElement {\n   \"id\": \"f.CF8596CF3572F4D96BD29481BCC04336.d.776697E7CEAFCCCBAB9B35277F6E0A77.e.791\",\n   \"using\": \"xpath\",\n   \"value\": \".//a[contains(@class,'V0OXxd')]\"\n}\n",
            "RESPONSE": "[1763013727.222][INFO]: [5fbd50b274790022917e320665b02ce4] RESPONSE FindChildElement ERROR no such element: Unable to locate element: {\"method\":\"xpath\",\"selector\":\".//a[contains(@class,'V0OXxd')]\"}\n  (Session info: chrome=142.0.7444.135)\n"
        },
        {
            "COMMAND": "[1763013727.226][INFO]: [5fbd50b274790022917e320665b02ce4] COMMAND FindChildElement {\n   \"id\": \"f.CF8596CF3572F4D96BD29481BCC04336.d.776697E7CEAFCCCBAB9B35277F6E0A77.e.792\",\n   \"using\": \"xpath\",\n   \"value\": \".//a[contains(@class,'s1Q9rs')]\"\n}\n",
            "RESPONSE": "[1763013757.235][INFO]: [5fbd50b274790022917e320665b02ce4] RESPONSE FindChildElement ERROR no such element: Unable to locate element: {\"method\":\"xpath\",\"selector\":\".//a[contains(@class,'s1Q9rs')]\"}\n  (Session info: chrome=142.0.7444.135)\n"
        },
        {
            "COMMAND": "[1763013757.266][INFO]: [5fbd50b274790022917e320665b02ce4] COMMAND FindChildElement {\n   \"id\": \"f.CF8596CF3572F4D96BD29481BCC04336.d.776697E7CEAFCCCBAB9B35277F6E0A77.e.792\",\n   \"using\": \"xpath\",\n   \"value\": \".//a[contains(@class,'IRpwTa')]\"\n}\n",
            "RESPONSE": "[1763013787.277][INFO]: [5fbd50b274790022917e320665b02ce4] RESPONSE FindChildElement ERROR no such element: Unable to locate element: {\"method\":\"xpath\",\"selector\":\".//a[contains(@class,'IRpwTa')]\"}\n  (Session info: chrome=142.0.7444.135)\n"
        },
        {
            "COMMAND": "[1763013787.293][INFO]: [5fbd50b274790022917e320665b02ce4] COMMAND FindChildElement {\n   \"id\": \"f.CF8596CF3572F4D96BD29481BCC04336.d.776697E7CEAFCCCBAB9B35277F6E0A77.e.792\",\n   \"using\": \"xpath\",\n   \"value\": \".//a[contains(@class,'V0OXxd')]\"\n}\n",
            "RESPONSE": "[1763013817.322][INFO]: [5fbd50b274790022917e320665b02ce4] RESPONSE FindChildElement ERROR no such element: Unable to locate element: {\"method\":\"xpath\",\"selector\":\".//a[contains(@class,'V0OXxd')]\"}\n  (Session info: chrome=142.0.7444.135)\n"
        },
        {
            "COMMAND": "[1763013817.365][INFO]: [5fbd50b274790022917e320665b02ce4] COMMAND FindChildElement {\n   \"id\": \"f.CF8596CF3572F4D96BD29481BCC04336.d.776697E7CEAFCCCBAB9B35277F6E0A77.e.793\",\n   \"using\": \"xpath\",\n   \"value\": \".//a[contains(@class,'s1Q9rs')]\"\n}\n",
            "RESPONSE": "[1763013847.392][INFO]: [5fbd50b274790022917e320665b02ce4] RESPONSE FindChildElement ERROR no such element: Unable to locate element: {\"method\":\"xpath\",\"selector\":\".//a[contains(@class,'s1Q9rs')]\"}\n  (Session info: chrome=142.0.7444.135)\n"
        },
        {
            "COMMAND": "[1763013847.407][INFO]: [5fbd50b274790022917e320665b02ce4] COMMAND FindChildElement {\n   \"id\": \"f.CF8596CF3572F4D96BD29481BCC04336.d.776697E7CEAFCCCBAB9B35277F6E0A77.e.793\",\n   \"using\": \"xpath\",\n   \"value\": \".//a[contains(@class,'IRpwTa')]\"\n}\n",
            "RESPONSE": "[1763013877.433][INFO]: [5fbd50b274790022917e320665b02ce4] RESPONSE FindChildElement ERROR no such element: Unable to locate element: {\"method\":\"xpath\",\"selector\":\".//a[contains(@class,'IRpwTa')]\"}\n  (Session info: chrome=142.0.7444.135)\n"
        },
        {
            "COMMAND": "[1763013877.528][INFO]: [5fbd50b274790022917e320665b02ce4] COMMAND FindChildElement {\n   \"id\": \"f.CF8596CF3572F4D96BD29481BCC04336.d.776697E7CEAFCCCBAB9B35277F6E0A77.e.793\",\n   \"using\": \"xpath\",\n   \"value\": \".//a[contains(@class,'V0OXxd')]\"\n}\n",
            "RESPONSE": "[1763013907.570][INFO]: [5fbd50b274790022917e320665b02ce4] RESPONSE FindChildElement ERROR no such element: Unable to locate element: {\"method\":\"xpath\",\"selector\":\".//a[contains(@class,'V0OXxd')]\"}\n  (Session info: chrome=142.0.7444.135)\n"
        },
        {
            "COMMAND": "[1763013907.573][INFO]: [5fbd50b274790022917e320665b02ce4] COMMAND FindChildElement {\n   \"id\": \"f.CF8596CF3572F4D96BD29481BCC04336.d.776697E7CEAFCCCBAB9B35277F6E0A77.e.794\",\n   \"using\": \"xpath\",\n   \"value\": \".//a[contains(@class,'s1Q9rs')]\"\n}\n",
            "RESPONSE": "[1763013937.609][INFO]: [5fbd50b274790022917e320665b02ce4] RESPONSE FindChildElement ERROR no such element: Unable to locate element: {\"method\":\"xpath\",\"selector\":\".//a[contains(@class,'s1Q9rs')]\"}\n  (Session info: chrome=142.0.7444.135)\n"
        },
        {
            "COMMAND": "[1763013937.612][INFO]: [5fbd50b274790022917e320665b02ce4] COMMAND FindChildElement {\n   \"id\": \"f.CF8596CF3572F4D96BD29481BCC04336.d.776697E7CEAFCCCBAB9B35277F6E0A77.e.794\",\n   \"using\": \"xpath\",\n   \"value\": \".//a[contains(@class,'IRpwTa')]\"\n}\n",
            "RESPONSE": "[1763013967.668][INFO]: [5fbd50b274790022917e320665b02ce4] RESPONSE FindChildElement ERROR no such element: Unable to locate element: {\"method\":\"xpath\",\"selector\":\".//a[contains(@class,'IRpwTa')]\"}\n  (Session info: chrome=142.0.7444.135)\n"
        },
        {
            "COMMAND": "[1763013967.671][INFO]: [5fbd50b274790022917e320665b02ce4] COMMAND FindChildElement {\n   \"id\": \"f.CF8596CF3572F4D96BD29481BCC04336.d.776697E7CEAFCCCBAB9B35277F6E0A77.e.794\",\n   \"using\": \"xpath\",\n   \"value\": \".//a[contains(@class,'V0OXxd')]\"\n}\n",
            "RESPONSE": "[1763013997.686][INFO]: [5fbd50b274790022917e320665b02ce4] RESPONSE FindChildElement ERROR no such element: Unable to locate element: {\"method\":\"xpath\",\"selector\":\".//a[contains(@class,'V0OXxd')]\"}\n  (Session info: chrome=142.0.7444.135)\n"
        },
        {
            "COMMAND": "[1763013997.689][INFO]: [5fbd50b274790022917e320665b02ce4] COMMAND FindChildElement {\n   \"id\": \"f.CF8596CF3572F4D96BD29481BCC04336.d.776697E7CEAFCCCBAB9B35277F6E0A77.e.795\",\n   \"using\": \"xpath\",\n   \"value\": \".//a[contains(@class,'s1Q9rs')]\"\n}\n",
            "RESPONSE": "[1763014027.750][INFO]: [5fbd50b274790022917e320665b02ce4] RESPONSE FindChildElement ERROR no such element: Unable to locate element: {\"method\":\"xpath\",\"selector\":\".//a[contains(@class,'s1Q9rs')]\"}\n  (Session info: chrome=142.0.7444.135)\n"
        },
        {
            "COMMAND": "[1763014027.759][INFO]: [5fbd50b274790022917e320665b02ce4] COMMAND FindChildElement {\n   \"id\": \"f.CF8596CF3572F4D96BD29481BCC04336.d.776697E7CEAFCCCBAB9B35277F6E0A77.e.795\",\n   \"using\": \"xpath\",\n   \"value\": \".//a[contains(@class,'IRpwTa')]\"\n}\n",
            "RESPONSE": "[1763014057.785][INFO]: [5fbd50b274790022917e320665b02ce4] RESPONSE FindChildElement ERROR no such element: Unable to locate element: {\"method\":\"xpath\",\"selector\":\".//a[contains(@class,'IRpwTa')]\"}\n  (Session info: chrome=142.0.7444.135)\n"
        },
        {
            "COMMAND": "[1763014057.833][INFO]: [5fbd50b274790022917e320665b02ce4] COMMAND FindChildElement {\n   \"id\": \"f.CF8596CF3572F4D96BD29481BCC04336.d.776697E7CEAFCCCBAB9B35277F6E0A77.e.795\",\n   \"using\": \"xpath\",\n   \"value\": \".//a[contains(@class,'V0OXxd')]\"\n}\n",
            "RESPONSE": "[1763014087.868][INFO]: [5fbd50b274790022917e320665b02ce4] RESPONSE FindChildElement ERROR no such element: Unable to locate element: {\"method\":\"xpath\",\"selector\":\".//a[contains(@class,'V0OXxd')]\"}\n  (Session info: chrome=142.0.7444.135)\n"
        },
        {
            "COMMAND": "[1763014087.970][INFO]: [5fbd50b274790022917e320665b02ce4] COMMAND FindChildElement {\n   \"id\": \"f.CF8596CF3572F4D96BD29481BCC04336.d.776697E7CEAFCCCBAB9B35277F6E0A77.e.796\",\n   \"using\": \"xpath\",\n   \"value\": \".//a[contains(@class,'s1Q9rs')]\"\n}\n",
            "RESPONSE": "[1763014118.034][INFO]: [5fbd50b274790022917e320665b02ce4] RESPONSE FindChildElement ERROR no such element: Unable to locate element: {\"method\":\"xpath\",\"selector\":\".//a[contains(@class,'s1Q9rs')]\"}\n  (Session info: chrome=142.0.7444.135)\n"
        },
        {
            "COMMAND": "[1763014118.037][INFO]: [5fbd50b274790022917e320665b02ce4] COMMAND FindChildElement {\n   \"id\": \"f.CF8596CF3572F4D96BD29481BCC04336.d.776697E7CEAFCCCBAB9B35277F6E0A77.e.796\",\n   \"using\": \"xpath\",\n   \"value\": \".//a[contains(@class,'IRpwTa')]\"\n}\n",
            "RESPONSE": "[1763014148.044][INFO]: [5fbd50b274790022917e320665b02ce4] RESPONSE FindChildElement ERROR no such element: Unable to locate element: {\"method\":\"xpath\",\"selector\":\".//a[contains(@class,'IRpwTa')]\"}\n  (Session info: chrome=142.0.7444.135)\n"
        },
        {
            "COMMAND": "[1763014148.047][INFO]: [5fbd50b274790022917e320665b02ce4] COMMAND FindChildElement {\n   \"id\": \"f.CF8596CF3572F4D96BD29481BCC04336.d.776697E7CEAFCCCBAB9B35277F6E0A77.e.796\",\n   \"using\": \"xpath\",\n   \"value\": \".//a[contains(@class,'V0OXxd')]\"\n}\n",
            "RESPONSE": "[1763014178.054][INFO]: [5fbd50b274790022917e320665b02ce4] RESPONSE FindChildElement ERROR no such element: Unable to locate element: {\"method\":\"xpath\",\"selector\":\".//a[contains(@class,'V0OXxd')]\"}\n  (Session info: chrome=142.0.7444.135)\n"
        }
    ]
}